{
  "library": "karoryfer.weresax",
  "format": "opus-48k",
  "sourceRepo": "https://github.com/zulfikarbarbora-outl/karoryfer.weresax",
  "previewRepo": "https://github.com/zulfikarbarbora-outl/weresax-opus-48",
  "branch": "master",
  "fileCount": 256,
  "baseUrl": "https://raw.githubusercontent.com/zulfikarbarbora-outl/weresax-opus-48/master/",
  "files": [
    {
      "file": "a2_f_rr1_cnd.opus",
      "name": "a2_f_rr1_cnd.opus",
      "url": "https://raw.githubusercontent.com/zulfikarbarbora-outl/weresax-opus-48/master/a2_f_rr1_cnd.opus",
      "size": 51658,
      "note": "a2",
      "midiNote": 45,
      "velocity": null,
      "dynamic": null,
      "roundRobin": 1
    },
    {
      "file": "a2_f_rr1_dnm.opus",
      "name": "a2_f_rr1_dnm.opus",
      "url": "https://raw.githubusercontent.com/zulfikarbarbora-outl/weresax-opus-48/master/a2_f_rr1_dnm.opus",
      "size": 53923,
      "note": "a2",
      "midiNote": 45,
      "velocity": null,
      "dynamic": null,
      "roundRobin": 1
    },
    {
      "file": "a2_f_rr2_cnd.opus",
      "name": "a2_f_rr2_cnd.opus",
      "url": "https://raw.githubusercontent.com/zulfikarbarbora-outl/weresax-opus-48/master/a2_f_rr2_cnd.opus",
      "size": 48350,
      "note": "a2",
      "midiNote": 45,
      "velocity": null,
      "dynamic": null,
      "roundRobin": 2
    },
    {
      "file": "a2_f_rr2_dnm.opus",
      "name": "a2_f_rr2_dnm.opus",
      "url": "https://raw.githubusercontent.com/zulfikarbarbora-outl/weresax-opus-48/master/a2_f_rr2_dnm.opus",
      "size": 51652,
      "note": "a2",
      "midiNote": 45,
      "velocity": null,
      "dynamic": null,
      "roundRobin": 2
    },
    {
      "file": "a2_p_rr1_cnd.opus",
      "name": "a2_p_rr1_cnd.opus",
      "url": "https://raw.githubusercontent.com/zulfikarbarbora-outl/weresax-opus-48/master/a2_p_rr1_cnd.opus",
      "size": 43380,
      "note": "a2",
      "midiNote": 45,
      "velocity": null,
      "dynamic": null,
      "roundRobin": 1
    },
    {
      "file": "a2_p_rr1_dnm.opus",
      "name": "a2_p_rr1_dnm.opus",
      "url": "https://raw.githubusercontent.com/zulfikarbarbora-outl/weresax-opus-48/master/a2_p_rr1_dnm.opus",
      "size": 48338,
      "note": "a2",
      "midiNote": 45,
      "velocity": null,
      "dynamic": null,
      "roundRobin": 1
    },
    {
      "file": "a2_p_rr2_cnd.opus",
      "name": "a2_p_rr2_cnd.opus",
      "url": "https://raw.githubusercontent.com/zulfikarbarbora-outl/weresax-opus-48/master/a2_p_rr2_cnd.opus",
      "size": 47039,
      "note": "a2",
      "midiNote": 45,
      "velocity": null,
      "dynamic": null,
      "roundRobin": 2
    },
    {
      "file": "a2_p_rr2_dnm.opus",
      "name": "a2_p_rr2_dnm.opus",
      "url": "https://raw.githubusercontent.com/zulfikarbarbora-outl/weresax-opus-48/master/a2_p_rr2_dnm.opus",
      "size": 52080,
      "note": "a2",
      "midiNote": 45,
      "velocity": null,
      "dynamic": null,
      "roundRobin": 2
    },
    {
      "file": "a3_f_rr1_cnd.opus",
      "name": "a3_f_rr1_cnd.opus",
      "url": "https://raw.githubusercontent.com/zulfikarbarbora-outl/weresax-opus-48/master/a3_f_rr1_cnd.opus",
      "size": 59741,
      "note": "a3",
      "midiNote": 57,
      "velocity": null,
      "dynamic": null,
      "roundRobin": 1
    },
    {
      "file": "a3_f_rr1_dnm.opus",
      "name": "a3_f_rr1_dnm.opus",
      "url": "https://raw.githubusercontent.com/zulfikarbarbora-outl/weresax-opus-48/master/a3_f_rr1_dnm.opus",
      "size": 63229,
      "note": "a3",
      "midiNote": 57,
      "velocity": null,
      "dynamic": null,
      "roundRobin": 1
    },
    {
      "file": "a3_f_rr2_cnd.opus",
      "name": "a3_f_rr2_cnd.opus",
      "url": "https://raw.githubusercontent.com/zulfikarbarbora-outl/weresax-opus-48/master/a3_f_rr2_cnd.opus",
      "size": 59620,
      "note": "a3",
      "midiNote": 57,
      "velocity": null,
      "dynamic": null,
      "roundRobin": 2
    },
    {
      "file": "a3_f_rr2_dnm.opus",
      "name": "a3_f_rr2_dnm.opus",
      "url": "https://raw.githubusercontent.com/zulfikarbarbora-outl/weresax-opus-48/master/a3_f_rr2_dnm.opus",
      "size": 59618,
      "note": "a3",
      "midiNote": 57,
      "velocity": null,
      "dynamic": null,
      "roundRobin": 2
    },
    {
      "file": "a3_p_rr1_cnd.opus",
      "name": "a3_p_rr1_cnd.opus",
      "url": "https://raw.githubusercontent.com/zulfikarbarbora-outl/weresax-opus-48/master/a3_p_rr1_cnd.opus",
      "size": 42866,
      "note": "a3",
      "midiNote": 57,
      "velocity": null,
      "dynamic": null,
      "roundRobin": 1
    },
    {
      "file": "a3_p_rr1_dnm.opus",
      "name": "a3_p_rr1_dnm.opus",
      "url": "https://raw.githubusercontent.com/zulfikarbarbora-outl/weresax-opus-48/master/a3_p_rr1_dnm.opus",
      "size": 48307,
      "note": "a3",
      "midiNote": 57,
      "velocity": null,
      "dynamic": null,
      "roundRobin": 1
    },
    {
      "file": "a3_p_rr2_cnd.opus",
      "name": "a3_p_rr2_cnd.opus",
      "url": "https://raw.githubusercontent.com/zulfikarbarbora-outl/weresax-opus-48/master/a3_p_rr2_cnd.opus",
      "size": 54326,
      "note": "a3",
      "midiNote": 57,
      "velocity": null,
      "dynamic": null,
      "roundRobin": 2
    },
    {
      "file": "a3_p_rr2_dnm.opus",
      "name": "a3_p_rr2_dnm.opus",
      "url": "https://raw.githubusercontent.com/zulfikarbarbora-outl/weresax-opus-48/master/a3_p_rr2_dnm.opus",
      "size": 55668,
      "note": "a3",
      "midiNote": 57,
      "velocity": null,
      "dynamic": null,
      "roundRobin": 2
    },
    {
      "file": "ab2_f_rr1_cnd.opus",
      "name": "ab2_f_rr1_cnd.opus",
      "url": "https://raw.githubusercontent.com/zulfikarbarbora-outl/weresax-opus-48/master/ab2_f_rr1_cnd.opus",
      "size": 57349,
      "note": "ab2",
      "midiNote": 44,
      "velocity": null,
      "dynamic": null,
      "roundRobin": 1
    },
    {
      "file": "ab2_f_rr1_dnm.opus",
      "name": "ab2_f_rr1_dnm.opus",
      "url": "https://raw.githubusercontent.com/zulfikarbarbora-outl/weresax-opus-48/master/ab2_f_rr1_dnm.opus",
      "size": 58148,
      "note": "ab2",
      "midiNote": 44,
      "velocity": null,
      "dynamic": null,
      "roundRobin": 1
    },
    {
      "file": "ab2_f_rr2_cnd.opus",
      "name": "ab2_f_rr2_cnd.opus",
      "url": "https://raw.githubusercontent.com/zulfikarbarbora-outl/weresax-opus-48/master/ab2_f_rr2_cnd.opus",
      "size": 53565,
      "note": "ab2",
      "midiNote": 44,
      "velocity": null,
      "dynamic": null,
      "roundRobin": 2
    },
    {
      "file": "ab2_f_rr2_dnm.opus",
      "name": "ab2_f_rr2_dnm.opus",
      "url": "https://raw.githubusercontent.com/zulfikarbarbora-outl/weresax-opus-48/master/ab2_f_rr2_dnm.opus",
      "size": 50030,
      "note": "ab2",
      "midiNote": 44,
      "velocity": null,
      "dynamic": null,
      "roundRobin": 2
    },
    {
      "file": "ab2_p_rr1_cnd.opus",
      "name": "ab2_p_rr1_cnd.opus",
      "url": "https://raw.githubusercontent.com/zulfikarbarbora-outl/weresax-opus-48/master/ab2_p_rr1_cnd.opus",
      "size": 49337,
      "note": "ab2",
      "midiNote": 44,
      "velocity": null,
      "dynamic": null,
      "roundRobin": 1
    },
    {
      "file": "ab2_p_rr1_dnm.opus",
      "name": "ab2_p_rr1_dnm.opus",
      "url": "https://raw.githubusercontent.com/zulfikarbarbora-outl/weresax-opus-48/master/ab2_p_rr1_dnm.opus",
      "size": 49248,
      "note": "ab2",
      "midiNote": 44,
      "velocity": null,
      "dynamic": null,
      "roundRobin": 1
    },
    {
      "file": "ab2_p_rr2_cnd.opus",
      "name": "ab2_p_rr2_cnd.opus",
      "url": "https://raw.githubusercontent.com/zulfikarbarbora-outl/weresax-opus-48/master/ab2_p_rr2_cnd.opus",
      "size": 50613,
      "note": "ab2",
      "midiNote": 44,
      "velocity": null,
      "dynamic": null,
      "roundRobin": 2
    },
    {
      "file": "ab2_p_rr2_dnm.opus",
      "name": "ab2_p_rr2_dnm.opus",
      "url": "https://raw.githubusercontent.com/zulfikarbarbora-outl/weresax-opus-48/master/ab2_p_rr2_dnm.opus",
      "size": 50034,
      "note": "ab2",
      "midiNote": 44,
      "velocity": null,
      "dynamic": null,
      "roundRobin": 2
    },
    {
      "file": "ab3_f_rr1_cnd.opus",
      "name": "ab3_f_rr1_cnd.opus",
      "url": "https://raw.githubusercontent.com/zulfikarbarbora-outl/weresax-opus-48/master/ab3_f_rr1_cnd.opus",
      "size": 68484,
      "note": "ab3",
      "midiNote": 56,
      "velocity": null,
      "dynamic": null,
      "roundRobin": 1
    },
    {
      "file": "ab3_f_rr1_dnm.opus",
      "name": "ab3_f_rr1_dnm.opus",
      "url": "https://raw.githubusercontent.com/zulfikarbarbora-outl/weresax-opus-48/master/ab3_f_rr1_dnm.opus",
      "size": 66726,
      "note": "ab3",
      "midiNote": 56,
      "velocity": null,
      "dynamic": null,
      "roundRobin": 1
    },
    {
      "file": "ab3_f_rr2_cnd.opus",
      "name": "ab3_f_rr2_cnd.opus",
      "url": "https://raw.githubusercontent.com/zulfikarbarbora-outl/weresax-opus-48/master/ab3_f_rr2_cnd.opus",
      "size": 68962,
      "note": "ab3",
      "midiNote": 56,
      "velocity": null,
      "dynamic": null,
      "roundRobin": 2
    },
    {
      "file": "ab3_f_rr2_dnm.opus",
      "name": "ab3_f_rr2_dnm.opus",
      "url": "https://raw.githubusercontent.com/zulfikarbarbora-outl/weresax-opus-48/master/ab3_f_rr2_dnm.opus",
      "size": 68618,
      "note": "ab3",
      "midiNote": 56,
      "velocity": null,
      "dynamic": null,
      "roundRobin": 2
    },
    {
      "file": "ab3_p_rr1_cnd.opus",
      "name": "ab3_p_rr1_cnd.opus",
      "url": "https://raw.githubusercontent.com/zulfikarbarbora-outl/weresax-opus-48/master/ab3_p_rr1_cnd.opus",
      "size": 55623,
      "note": "ab3",
      "midiNote": 56,
      "velocity": null,
      "dynamic": null,
      "roundRobin": 1
    },
    {
      "file": "ab3_p_rr1_dnm.opus",
      "name": "ab3_p_rr1_dnm.opus",
      "url": "https://raw.githubusercontent.com/zulfikarbarbora-outl/weresax-opus-48/master/ab3_p_rr1_dnm.opus",
      "size": 54867,
      "note": "ab3",
      "midiNote": 56,
      "velocity": null,
      "dynamic": null,
      "roundRobin": 1
    },
    {
      "file": "ab3_p_rr2_cnd.opus",
      "name": "ab3_p_rr2_cnd.opus",
      "url": "https://raw.githubusercontent.com/zulfikarbarbora-outl/weresax-opus-48/master/ab3_p_rr2_cnd.opus",
      "size": 49846,
      "note": "ab3",
      "midiNote": 56,
      "velocity": null,
      "dynamic": null,
      "roundRobin": 2
    },
    {
      "file": "ab3_p_rr2_dnm.opus",
      "name": "ab3_p_rr2_dnm.opus",
      "url": "https://raw.githubusercontent.com/zulfikarbarbora-outl/weresax-opus-48/master/ab3_p_rr2_dnm.opus",
      "size": 49814,
      "note": "ab3",
      "midiNote": 56,
      "velocity": null,
      "dynamic": null,
      "roundRobin": 2
    },
    {
      "file": "ab4_f_rr1_cnd.opus",
      "name": "ab4_f_rr1_cnd.opus",
      "url": "https://raw.githubusercontent.com/zulfikarbarbora-outl/weresax-opus-48/master/ab4_f_rr1_cnd.opus",
      "size": 57584,
      "note": "ab4",
      "midiNote": 68,
      "velocity": null,
      "dynamic": null,
      "roundRobin": 1
    },
    {
      "file": "ab4_f_rr1_dnm.opus",
      "name": "ab4_f_rr1_dnm.opus",
      "url": "https://raw.githubusercontent.com/zulfikarbarbora-outl/weresax-opus-48/master/ab4_f_rr1_dnm.opus",
      "size": 57766,
      "note": "ab4",
      "midiNote": 68,
      "velocity": null,
      "dynamic": null,
      "roundRobin": 1
    },
    {
      "file": "ab4_f_rr2_cnd.opus",
      "name": "ab4_f_rr2_cnd.opus",
      "url": "https://raw.githubusercontent.com/zulfikarbarbora-outl/weresax-opus-48/master/ab4_f_rr2_cnd.opus",
      "size": 53999,
      "note": "ab4",
      "midiNote": 68,
      "velocity": null,
      "dynamic": null,
      "roundRobin": 2
    },
    {
      "file": "ab4_f_rr2_dnm.opus",
      "name": "ab4_f_rr2_dnm.opus",
      "url": "https://raw.githubusercontent.com/zulfikarbarbora-outl/weresax-opus-48/master/ab4_f_rr2_dnm.opus",
      "size": 53523,
      "note": "ab4",
      "midiNote": 68,
      "velocity": null,
      "dynamic": null,
      "roundRobin": 2
    },
    {
      "file": "ab4_p_rr1_cnd.opus",
      "name": "ab4_p_rr1_cnd.opus",
      "url": "https://raw.githubusercontent.com/zulfikarbarbora-outl/weresax-opus-48/master/ab4_p_rr1_cnd.opus",
      "size": 40429,
      "note": "ab4",
      "midiNote": 68,
      "velocity": null,
      "dynamic": null,
      "roundRobin": 1
    },
    {
      "file": "ab4_p_rr1_dnm.opus",
      "name": "ab4_p_rr1_dnm.opus",
      "url": "https://raw.githubusercontent.com/zulfikarbarbora-outl/weresax-opus-48/master/ab4_p_rr1_dnm.opus",
      "size": 40939,
      "note": "ab4",
      "midiNote": 68,
      "velocity": null,
      "dynamic": null,
      "roundRobin": 1
    },
    {
      "file": "ab4_p_rr2_cnd.opus",
      "name": "ab4_p_rr2_cnd.opus",
      "url": "https://raw.githubusercontent.com/zulfikarbarbora-outl/weresax-opus-48/master/ab4_p_rr2_cnd.opus",
      "size": 55664,
      "note": "ab4",
      "midiNote": 68,
      "velocity": null,
      "dynamic": null,
      "roundRobin": 2
    },
    {
      "file": "ab4_p_rr2_dnm.opus",
      "name": "ab4_p_rr2_dnm.opus",
      "url": "https://raw.githubusercontent.com/zulfikarbarbora-outl/weresax-opus-48/master/ab4_p_rr2_dnm.opus",
      "size": 55537,
      "note": "ab4",
      "midiNote": 68,
      "velocity": null,
      "dynamic": null,
      "roundRobin": 2
    },
    {
      "file": "b2_f_rr1_cnd.opus",
      "name": "b2_f_rr1_cnd.opus",
      "url": "https://raw.githubusercontent.com/zulfikarbarbora-outl/weresax-opus-48/master/b2_f_rr1_cnd.opus",
      "size": 66000,
      "note": "b2",
      "midiNote": 47,
      "velocity": null,
      "dynamic": null,
      "roundRobin": 1
    },
    {
      "file": "b2_f_rr1_dnm.opus",
      "name": "b2_f_rr1_dnm.opus",
      "url": "https://raw.githubusercontent.com/zulfikarbarbora-outl/weresax-opus-48/master/b2_f_rr1_dnm.opus",
      "size": 66275,
      "note": "b2",
      "midiNote": 47,
      "velocity": null,
      "dynamic": null,
      "roundRobin": 1
    },
    {
      "file": "b2_f_rr2_cnd.opus",
      "name": "b2_f_rr2_cnd.opus",
      "url": "https://raw.githubusercontent.com/zulfikarbarbora-outl/weresax-opus-48/master/b2_f_rr2_cnd.opus",
      "size": 56317,
      "note": "b2",
      "midiNote": 47,
      "velocity": null,
      "dynamic": null,
      "roundRobin": 2
    },
    {
      "file": "b2_f_rr2_dnm.opus",
      "name": "b2_f_rr2_dnm.opus",
      "url": "https://raw.githubusercontent.com/zulfikarbarbora-outl/weresax-opus-48/master/b2_f_rr2_dnm.opus",
      "size": 56071,
      "note": "b2",
      "midiNote": 47,
      "velocity": null,
      "dynamic": null,
      "roundRobin": 2
    },
    {
      "file": "b2_p_rr1_cnd.opus",
      "name": "b2_p_rr1_cnd.opus",
      "url": "https://raw.githubusercontent.com/zulfikarbarbora-outl/weresax-opus-48/master/b2_p_rr1_cnd.opus",
      "size": 49603,
      "note": "b2",
      "midiNote": 47,
      "velocity": null,
      "dynamic": null,
      "roundRobin": 1
    },
    {
      "file": "b2_p_rr1_dnm.opus",
      "name": "b2_p_rr1_dnm.opus",
      "url": "https://raw.githubusercontent.com/zulfikarbarbora-outl/weresax-opus-48/master/b2_p_rr1_dnm.opus",
      "size": 47939,
      "note": "b2",
      "midiNote": 47,
      "velocity": null,
      "dynamic": null,
      "roundRobin": 1
    },
    {
      "file": "b2_p_rr2_cnd.opus",
      "name": "b2_p_rr2_cnd.opus",
      "url": "https://raw.githubusercontent.com/zulfikarbarbora-outl/weresax-opus-48/master/b2_p_rr2_cnd.opus",
      "size": 51244,
      "note": "b2",
      "midiNote": 47,
      "velocity": null,
      "dynamic": null,
      "roundRobin": 2
    },
    {
      "file": "b2_p_rr2_dnm.opus",
      "name": "b2_p_rr2_dnm.opus",
      "url": "https://raw.githubusercontent.com/zulfikarbarbora-outl/weresax-opus-48/master/b2_p_rr2_dnm.opus",
      "size": 49337,
      "note": "b2",
      "midiNote": 47,
      "velocity": null,
      "dynamic": null,
      "roundRobin": 2
    },
    {
      "file": "b3_f_rr1_cnd.opus",
      "name": "b3_f_rr1_cnd.opus",
      "url": "https://raw.githubusercontent.com/zulfikarbarbora-outl/weresax-opus-48/master/b3_f_rr1_cnd.opus",
      "size": 62230,
      "note": "b3",
      "midiNote": 59,
      "velocity": null,
      "dynamic": null,
      "roundRobin": 1
    },
    {
      "file": "b3_f_rr1_dnm.opus",
      "name": "b3_f_rr1_dnm.opus",
      "url": "https://raw.githubusercontent.com/zulfikarbarbora-outl/weresax-opus-48/master/b3_f_rr1_dnm.opus",
      "size": 62898,
      "note": "b3",
      "midiNote": 59,
      "velocity": null,
      "dynamic": null,
      "roundRobin": 1
    },
    {
      "file": "b3_f_rr2_cnd.opus",
      "name": "b3_f_rr2_cnd.opus",
      "url": "https://raw.githubusercontent.com/zulfikarbarbora-outl/weresax-opus-48/master/b3_f_rr2_cnd.opus",
      "size": 61032,
      "note": "b3",
      "midiNote": 59,
      "velocity": null,
      "dynamic": null,
      "roundRobin": 2
    },
    {
      "file": "b3_f_rr2_dnm.opus",
      "name": "b3_f_rr2_dnm.opus",
      "url": "https://raw.githubusercontent.com/zulfikarbarbora-outl/weresax-opus-48/master/b3_f_rr2_dnm.opus",
      "size": 59959,
      "note": "b3",
      "midiNote": 59,
      "velocity": null,
      "dynamic": null,
      "roundRobin": 2
    },
    {
      "file": "b3_p_rr1_cnd.opus",
      "name": "b3_p_rr1_cnd.opus",
      "url": "https://raw.githubusercontent.com/zulfikarbarbora-outl/weresax-opus-48/master/b3_p_rr1_cnd.opus",
      "size": 54271,
      "note": "b3",
      "midiNote": 59,
      "velocity": null,
      "dynamic": null,
      "roundRobin": 1
    },
    {
      "file": "b3_p_rr1_dnm.opus",
      "name": "b3_p_rr1_dnm.opus",
      "url": "https://raw.githubusercontent.com/zulfikarbarbora-outl/weresax-opus-48/master/b3_p_rr1_dnm.opus",
      "size": 59801,
      "note": "b3",
      "midiNote": 59,
      "velocity": null,
      "dynamic": null,
      "roundRobin": 1
    },
    {
      "file": "b3_p_rr2_cnd.opus",
      "name": "b3_p_rr2_cnd.opus",
      "url": "https://raw.githubusercontent.com/zulfikarbarbora-outl/weresax-opus-48/master/b3_p_rr2_cnd.opus",
      "size": 57764,
      "note": "b3",
      "midiNote": 59,
      "velocity": null,
      "dynamic": null,
      "roundRobin": 2
    },
    {
      "file": "b3_p_rr2_dnm.opus",
      "name": "b3_p_rr2_dnm.opus",
      "url": "https://raw.githubusercontent.com/zulfikarbarbora-outl/weresax-opus-48/master/b3_p_rr2_dnm.opus",
      "size": 56859,
      "note": "b3",
      "midiNote": 59,
      "velocity": null,
      "dynamic": null,
      "roundRobin": 2
    },
    {
      "file": "bb2_f_rr1_cnd.opus",
      "name": "bb2_f_rr1_cnd.opus",
      "url": "https://raw.githubusercontent.com/zulfikarbarbora-outl/weresax-opus-48/master/bb2_f_rr1_cnd.opus",
      "size": 51568,
      "note": "bb2",
      "midiNote": 46,
      "velocity": null,
      "dynamic": null,
      "roundRobin": 1
    },
    {
      "file": "bb2_f_rr1_dnm.opus",
      "name": "bb2_f_rr1_dnm.opus",
      "url": "https://raw.githubusercontent.com/zulfikarbarbora-outl/weresax-opus-48/master/bb2_f_rr1_dnm.opus",
      "size": 51737,
      "note": "bb2",
      "midiNote": 46,
      "velocity": null,
      "dynamic": null,
      "roundRobin": 1
    },
    {
      "file": "bb2_f_rr2_cnd.opus",
      "name": "bb2_f_rr2_cnd.opus",
      "url": "https://raw.githubusercontent.com/zulfikarbarbora-outl/weresax-opus-48/master/bb2_f_rr2_cnd.opus",
      "size": 63694,
      "note": "bb2",
      "midiNote": 46,
      "velocity": null,
      "dynamic": null,
      "roundRobin": 2
    },
    {
      "file": "bb2_f_rr2_dnm.opus",
      "name": "bb2_f_rr2_dnm.opus",
      "url": "https://raw.githubusercontent.com/zulfikarbarbora-outl/weresax-opus-48/master/bb2_f_rr2_dnm.opus",
      "size": 66893,
      "note": "bb2",
      "midiNote": 46,
      "velocity": null,
      "dynamic": null,
      "roundRobin": 2
    },
    {
      "file": "bb2_p_rr1_cnd.opus",
      "name": "bb2_p_rr1_cnd.opus",
      "url": "https://raw.githubusercontent.com/zulfikarbarbora-outl/weresax-opus-48/master/bb2_p_rr1_cnd.opus",
      "size": 49060,
      "note": "bb2",
      "midiNote": 46,
      "velocity": null,
      "dynamic": null,
      "roundRobin": 1
    },
    {
      "file": "bb2_p_rr1_dnm.opus",
      "name": "bb2_p_rr1_dnm.opus",
      "url": "https://raw.githubusercontent.com/zulfikarbarbora-outl/weresax-opus-48/master/bb2_p_rr1_dnm.opus",
      "size": 50607,
      "note": "bb2",
      "midiNote": 46,
      "velocity": null,
      "dynamic": null,
      "roundRobin": 1
    },
    {
      "file": "bb2_p_rr2_cnd.opus",
      "name": "bb2_p_rr2_cnd.opus",
      "url": "https://raw.githubusercontent.com/zulfikarbarbora-outl/weresax-opus-48/master/bb2_p_rr2_cnd.opus",
      "size": 44546,
      "note": "bb2",
      "midiNote": 46,
      "velocity": null,
      "dynamic": null,
      "roundRobin": 2
    },
    {
      "file": "bb2_p_rr2_dnm.opus",
      "name": "bb2_p_rr2_dnm.opus",
      "url": "https://raw.githubusercontent.com/zulfikarbarbora-outl/weresax-opus-48/master/bb2_p_rr2_dnm.opus",
      "size": 45816,
      "note": "bb2",
      "midiNote": 46,
      "velocity": null,
      "dynamic": null,
      "roundRobin": 2
    },
    {
      "file": "bb3_f_rr1_cnd.opus",
      "name": "bb3_f_rr1_cnd.opus",
      "url": "https://raw.githubusercontent.com/zulfikarbarbora-outl/weresax-opus-48/master/bb3_f_rr1_cnd.opus",
      "size": 50880,
      "note": "bb3",
      "midiNote": 58,
      "velocity": null,
      "dynamic": null,
      "roundRobin": 1
    },
    {
      "file": "bb3_f_rr1_dnm.opus",
      "name": "bb3_f_rr1_dnm.opus",
      "url": "https://raw.githubusercontent.com/zulfikarbarbora-outl/weresax-opus-48/master/bb3_f_rr1_dnm.opus",
      "size": 52208,
      "note": "bb3",
      "midiNote": 58,
      "velocity": null,
      "dynamic": null,
      "roundRobin": 1
    },
    {
      "file": "bb3_f_rr2_cnd.opus",
      "name": "bb3_f_rr2_cnd.opus",
      "url": "https://raw.githubusercontent.com/zulfikarbarbora-outl/weresax-opus-48/master/bb3_f_rr2_cnd.opus",
      "size": 60672,
      "note": "bb3",
      "midiNote": 58,
      "velocity": null,
      "dynamic": null,
      "roundRobin": 2
    },
    {
      "file": "bb3_f_rr2_dnm.opus",
      "name": "bb3_f_rr2_dnm.opus",
      "url": "https://raw.githubusercontent.com/zulfikarbarbora-outl/weresax-opus-48/master/bb3_f_rr2_dnm.opus",
      "size": 59748,
      "note": "bb3",
      "midiNote": 58,
      "velocity": null,
      "dynamic": null,
      "roundRobin": 2
    },
    {
      "file": "bb3_p_rr1_cnd.opus",
      "name": "bb3_p_rr1_cnd.opus",
      "url": "https://raw.githubusercontent.com/zulfikarbarbora-outl/weresax-opus-48/master/bb3_p_rr1_cnd.opus",
      "size": 52606,
      "note": "bb3",
      "midiNote": 58,
      "velocity": null,
      "dynamic": null,
      "roundRobin": 1
    },
    {
      "file": "bb3_p_rr1_dnm.opus",
      "name": "bb3_p_rr1_dnm.opus",
      "url": "https://raw.githubusercontent.com/zulfikarbarbora-outl/weresax-opus-48/master/bb3_p_rr1_dnm.opus",
      "size": 52736,
      "note": "bb3",
      "midiNote": 58,
      "velocity": null,
      "dynamic": null,
      "roundRobin": 1
    },
    {
      "file": "bb3_p_rr2_cnd.opus",
      "name": "bb3_p_rr2_cnd.opus",
      "url": "https://raw.githubusercontent.com/zulfikarbarbora-outl/weresax-opus-48/master/bb3_p_rr2_cnd.opus",
      "size": 58583,
      "note": "bb3",
      "midiNote": 58,
      "velocity": null,
      "dynamic": null,
      "roundRobin": 2
    },
    {
      "file": "bb3_p_rr2_dnm.opus",
      "name": "bb3_p_rr2_dnm.opus",
      "url": "https://raw.githubusercontent.com/zulfikarbarbora-outl/weresax-opus-48/master/bb3_p_rr2_dnm.opus",
      "size": 64770,
      "note": "bb3",
      "midiNote": 58,
      "velocity": null,
      "dynamic": null,
      "roundRobin": 2
    },
    {
      "file": "c3_f_rr1_cnd.opus",
      "name": "c3_f_rr1_cnd.opus",
      "url": "https://raw.githubusercontent.com/zulfikarbarbora-outl/weresax-opus-48/master/c3_f_rr1_cnd.opus",
      "size": 56789,
      "note": "c3",
      "midiNote": 48,
      "velocity": null,
      "dynamic": null,
      "roundRobin": 1
    },
    {
      "file": "c3_f_rr1_dnm.opus",
      "name": "c3_f_rr1_dnm.opus",
      "url": "https://raw.githubusercontent.com/zulfikarbarbora-outl/weresax-opus-48/master/c3_f_rr1_dnm.opus",
      "size": 56759,
      "note": "c3",
      "midiNote": 48,
      "velocity": null,
      "dynamic": null,
      "roundRobin": 1
    },
    {
      "file": "c3_f_rr2_cnd.opus",
      "name": "c3_f_rr2_cnd.opus",
      "url": "https://raw.githubusercontent.com/zulfikarbarbora-outl/weresax-opus-48/master/c3_f_rr2_cnd.opus",
      "size": 60637,
      "note": "c3",
      "midiNote": 48,
      "velocity": null,
      "dynamic": null,
      "roundRobin": 2
    },
    {
      "file": "c3_f_rr2_dnm.opus",
      "name": "c3_f_rr2_dnm.opus",
      "url": "https://raw.githubusercontent.com/zulfikarbarbora-outl/weresax-opus-48/master/c3_f_rr2_dnm.opus",
      "size": 60725,
      "note": "c3",
      "midiNote": 48,
      "velocity": null,
      "dynamic": null,
      "roundRobin": 2
    },
    {
      "file": "c3_p_rr1_cnd.opus",
      "name": "c3_p_rr1_cnd.opus",
      "url": "https://raw.githubusercontent.com/zulfikarbarbora-outl/weresax-opus-48/master/c3_p_rr1_cnd.opus",
      "size": 44215,
      "note": "c3",
      "midiNote": 48,
      "velocity": null,
      "dynamic": null,
      "roundRobin": 1
    },
    {
      "file": "c3_p_rr1_dnm.opus",
      "name": "c3_p_rr1_dnm.opus",
      "url": "https://raw.githubusercontent.com/zulfikarbarbora-outl/weresax-opus-48/master/c3_p_rr1_dnm.opus",
      "size": 44406,
      "note": "c3",
      "midiNote": 48,
      "velocity": null,
      "dynamic": null,
      "roundRobin": 1
    },
    {
      "file": "c3_p_rr2_cnd.opus",
      "name": "c3_p_rr2_cnd.opus",
      "url": "https://raw.githubusercontent.com/zulfikarbarbora-outl/weresax-opus-48/master/c3_p_rr2_cnd.opus",
      "size": 43236,
      "note": "c3",
      "midiNote": 48,
      "velocity": null,
      "dynamic": null,
      "roundRobin": 2
    },
    {
      "file": "c3_p_rr2_dnm.opus",
      "name": "c3_p_rr2_dnm.opus",
      "url": "https://raw.githubusercontent.com/zulfikarbarbora-outl/weresax-opus-48/master/c3_p_rr2_dnm.opus",
      "size": 43338,
      "note": "c3",
      "midiNote": 48,
      "velocity": null,
      "dynamic": null,
      "roundRobin": 2
    },
    {
      "file": "c4_f_rr1_cnd.opus",
      "name": "c4_f_rr1_cnd.opus",
      "url": "https://raw.githubusercontent.com/zulfikarbarbora-outl/weresax-opus-48/master/c4_f_rr1_cnd.opus",
      "size": 60242,
      "note": "c4",
      "midiNote": 60,
      "velocity": null,
      "dynamic": null,
      "roundRobin": 1
    },
    {
      "file": "c4_f_rr1_dnm.opus",
      "name": "c4_f_rr1_dnm.opus",
      "url": "https://raw.githubusercontent.com/zulfikarbarbora-outl/weresax-opus-48/master/c4_f_rr1_dnm.opus",
      "size": 60357,
      "note": "c4",
      "midiNote": 60,
      "velocity": null,
      "dynamic": null,
      "roundRobin": 1
    },
    {
      "file": "c4_f_rr2_cnd.opus",
      "name": "c4_f_rr2_cnd.opus",
      "url": "https://raw.githubusercontent.com/zulfikarbarbora-outl/weresax-opus-48/master/c4_f_rr2_cnd.opus",
      "size": 66428,
      "note": "c4",
      "midiNote": 60,
      "velocity": null,
      "dynamic": null,
      "roundRobin": 2
    },
    {
      "file": "c4_f_rr2_dnm.opus",
      "name": "c4_f_rr2_dnm.opus",
      "url": "https://raw.githubusercontent.com/zulfikarbarbora-outl/weresax-opus-48/master/c4_f_rr2_dnm.opus",
      "size": 66342,
      "note": "c4",
      "midiNote": 60,
      "velocity": null,
      "dynamic": null,
      "roundRobin": 2
    },
    {
      "file": "c4_p_rr1_cnd.opus",
      "name": "c4_p_rr1_cnd.opus",
      "url": "https://raw.githubusercontent.com/zulfikarbarbora-outl/weresax-opus-48/master/c4_p_rr1_cnd.opus",
      "size": 59683,
      "note": "c4",
      "midiNote": 60,
      "velocity": null,
      "dynamic": null,
      "roundRobin": 1
    },
    {
      "file": "c4_p_rr1_dnm.opus",
      "name": "c4_p_rr1_dnm.opus",
      "url": "https://raw.githubusercontent.com/zulfikarbarbora-outl/weresax-opus-48/master/c4_p_rr1_dnm.opus",
      "size": 58837,
      "note": "c4",
      "midiNote": 60,
      "velocity": null,
      "dynamic": null,
      "roundRobin": 1
    },
    {
      "file": "c4_p_rr2_cnd.opus",
      "name": "c4_p_rr2_cnd.opus",
      "url": "https://raw.githubusercontent.com/zulfikarbarbora-outl/weresax-opus-48/master/c4_p_rr2_cnd.opus",
      "size": 61514,
      "note": "c4",
      "midiNote": 60,
      "velocity": null,
      "dynamic": null,
      "roundRobin": 2
    },
    {
      "file": "c4_p_rr2_dnm.opus",
      "name": "c4_p_rr2_dnm.opus",
      "url": "https://raw.githubusercontent.com/zulfikarbarbora-outl/weresax-opus-48/master/c4_p_rr2_dnm.opus",
      "size": 63638,
      "note": "c4",
      "midiNote": 60,
      "velocity": null,
      "dynamic": null,
      "roundRobin": 2
    },
    {
      "file": "d2_f_rr1_cnd.opus",
      "name": "d2_f_rr1_cnd.opus",
      "url": "https://raw.githubusercontent.com/zulfikarbarbora-outl/weresax-opus-48/master/d2_f_rr1_cnd.opus",
      "size": 43991,
      "note": "d2",
      "midiNote": 38,
      "velocity": null,
      "dynamic": null,
      "roundRobin": 1
    },
    {
      "file": "d2_f_rr1_dnm.opus",
      "name": "d2_f_rr1_dnm.opus",
      "url": "https://raw.githubusercontent.com/zulfikarbarbora-outl/weresax-opus-48/master/d2_f_rr1_dnm.opus",
      "size": 50094,
      "note": "d2",
      "midiNote": 38,
      "velocity": null,
      "dynamic": null,
      "roundRobin": 1
    },
    {
      "file": "d2_f_rr2_cnd.opus",
      "name": "d2_f_rr2_cnd.opus",
      "url": "https://raw.githubusercontent.com/zulfikarbarbora-outl/weresax-opus-48/master/d2_f_rr2_cnd.opus",
      "size": 44520,
      "note": "d2",
      "midiNote": 38,
      "velocity": null,
      "dynamic": null,
      "roundRobin": 2
    },
    {
      "file": "d2_f_rr2_dnm.opus",
      "name": "d2_f_rr2_dnm.opus",
      "url": "https://raw.githubusercontent.com/zulfikarbarbora-outl/weresax-opus-48/master/d2_f_rr2_dnm.opus",
      "size": 52600,
      "note": "d2",
      "midiNote": 38,
      "velocity": null,
      "dynamic": null,
      "roundRobin": 2
    },
    {
      "file": "d2_p_rr1_cnd.opus",
      "name": "d2_p_rr1_cnd.opus",
      "url": "https://raw.githubusercontent.com/zulfikarbarbora-outl/weresax-opus-48/master/d2_p_rr1_cnd.opus",
      "size": 40077,
      "note": "d2",
      "midiNote": 38,
      "velocity": null,
      "dynamic": null,
      "roundRobin": 1
    },
    {
      "file": "d2_p_rr1_dnm.opus",
      "name": "d2_p_rr1_dnm.opus",
      "url": "https://raw.githubusercontent.com/zulfikarbarbora-outl/weresax-opus-48/master/d2_p_rr1_dnm.opus",
      "size": 43410,
      "note": "d2",
      "midiNote": 38,
      "velocity": null,
      "dynamic": null,
      "roundRobin": 1
    },
    {
      "file": "d2_p_rr2_cnd.opus",
      "name": "d2_p_rr2_cnd.opus",
      "url": "https://raw.githubusercontent.com/zulfikarbarbora-outl/weresax-opus-48/master/d2_p_rr2_cnd.opus",
      "size": 52536,
      "note": "d2",
      "midiNote": 38,
      "velocity": null,
      "dynamic": null,
      "roundRobin": 2
    },
    {
      "file": "d2_p_rr2_dnm.opus",
      "name": "d2_p_rr2_dnm.opus",
      "url": "https://raw.githubusercontent.com/zulfikarbarbora-outl/weresax-opus-48/master/d2_p_rr2_dnm.opus",
      "size": 58553,
      "note": "d2",
      "midiNote": 38,
      "velocity": null,
      "dynamic": null,
      "roundRobin": 2
    },
    {
      "file": "d3_f_rr1_cnd.opus",
      "name": "d3_f_rr1_cnd.opus",
      "url": "https://raw.githubusercontent.com/zulfikarbarbora-outl/weresax-opus-48/master/d3_f_rr1_cnd.opus",
      "size": 65135,
      "note": "d3",
      "midiNote": 50,
      "velocity": null,
      "dynamic": null,
      "roundRobin": 1
    },
    {
      "file": "d3_f_rr1_dnm.opus",
      "name": "d3_f_rr1_dnm.opus",
      "url": "https://raw.githubusercontent.com/zulfikarbarbora-outl/weresax-opus-48/master/d3_f_rr1_dnm.opus",
      "size": 63182,
      "note": "d3",
      "midiNote": 50,
      "velocity": null,
      "dynamic": null,
      "roundRobin": 1
    },
    {
      "file": "d3_f_rr2_cnd.opus",
      "name": "d3_f_rr2_cnd.opus",
      "url": "https://raw.githubusercontent.com/zulfikarbarbora-outl/weresax-opus-48/master/d3_f_rr2_cnd.opus",
      "size": 61211,
      "note": "d3",
      "midiNote": 50,
      "velocity": null,
      "dynamic": null,
      "roundRobin": 2
    },
    {
      "file": "d3_f_rr2_dnm.opus",
      "name": "d3_f_rr2_dnm.opus",
      "url": "https://raw.githubusercontent.com/zulfikarbarbora-outl/weresax-opus-48/master/d3_f_rr2_dnm.opus",
      "size": 62755,
      "note": "d3",
      "midiNote": 50,
      "velocity": null,
      "dynamic": null,
      "roundRobin": 2
    },
    {
      "file": "d3_p_rr1_cnd.opus",
      "name": "d3_p_rr1_cnd.opus",
      "url": "https://raw.githubusercontent.com/zulfikarbarbora-outl/weresax-opus-48/master/d3_p_rr1_cnd.opus",
      "size": 49838,
      "note": "d3",
      "midiNote": 50,
      "velocity": null,
      "dynamic": null,
      "roundRobin": 1
    },
    {
      "file": "d3_p_rr1_dnm.opus",
      "name": "d3_p_rr1_dnm.opus",
      "url": "https://raw.githubusercontent.com/zulfikarbarbora-outl/weresax-opus-48/master/d3_p_rr1_dnm.opus",
      "size": 51125,
      "note": "d3",
      "midiNote": 50,
      "velocity": null,
      "dynamic": null,
      "roundRobin": 1
    },
    {
      "file": "d3_p_rr2_cnd.opus",
      "name": "d3_p_rr2_cnd.opus",
      "url": "https://raw.githubusercontent.com/zulfikarbarbora-outl/weresax-opus-48/master/d3_p_rr2_cnd.opus",
      "size": 51145,
      "note": "d3",
      "midiNote": 50,
      "velocity": null,
      "dynamic": null,
      "roundRobin": 2
    },
    {
      "file": "d3_p_rr2_dnm.opus",
      "name": "d3_p_rr2_dnm.opus",
      "url": "https://raw.githubusercontent.com/zulfikarbarbora-outl/weresax-opus-48/master/d3_p_rr2_dnm.opus",
      "size": 51951,
      "note": "d3",
      "midiNote": 50,
      "velocity": null,
      "dynamic": null,
      "roundRobin": 2
    },
    {
      "file": "d4_f_rr1_cnd.opus",
      "name": "d4_f_rr1_cnd.opus",
      "url": "https://raw.githubusercontent.com/zulfikarbarbora-outl/weresax-opus-48/master/d4_f_rr1_cnd.opus",
      "size": 70704,
      "note": "d4",
      "midiNote": 62,
      "velocity": null,
      "dynamic": null,
      "roundRobin": 1
    },
    {
      "file": "d4_f_rr1_dnm.opus",
      "name": "d4_f_rr1_dnm.opus",
      "url": "https://raw.githubusercontent.com/zulfikarbarbora-outl/weresax-opus-48/master/d4_f_rr1_dnm.opus",
      "size": 69050,
      "note": "d4",
      "midiNote": 62,
      "velocity": null,
      "dynamic": null,
      "roundRobin": 1
    },
    {
      "file": "d4_f_rr2_cnd.opus",
      "name": "d4_f_rr2_cnd.opus",
      "url": "https://raw.githubusercontent.com/zulfikarbarbora-outl/weresax-opus-48/master/d4_f_rr2_cnd.opus",
      "size": 56537,
      "note": "d4",
      "midiNote": 62,
      "velocity": null,
      "dynamic": null,
      "roundRobin": 2
    },
    {
      "file": "d4_f_rr2_dnm.opus",
      "name": "d4_f_rr2_dnm.opus",
      "url": "https://raw.githubusercontent.com/zulfikarbarbora-outl/weresax-opus-48/master/d4_f_rr2_dnm.opus",
      "size": 52910,
      "note": "d4",
      "midiNote": 62,
      "velocity": null,
      "dynamic": null,
      "roundRobin": 2
    },
    {
      "file": "d4_p_rr1_cnd.opus",
      "name": "d4_p_rr1_cnd.opus",
      "url": "https://raw.githubusercontent.com/zulfikarbarbora-outl/weresax-opus-48/master/d4_p_rr1_cnd.opus",
      "size": 50550,
      "note": "d4",
      "midiNote": 62,
      "velocity": null,
      "dynamic": null,
      "roundRobin": 1
    },
    {
      "file": "d4_p_rr1_dnm.opus",
      "name": "d4_p_rr1_dnm.opus",
      "url": "https://raw.githubusercontent.com/zulfikarbarbora-outl/weresax-opus-48/master/d4_p_rr1_dnm.opus",
      "size": 49345,
      "note": "d4",
      "midiNote": 62,
      "velocity": null,
      "dynamic": null,
      "roundRobin": 1
    },
    {
      "file": "d4_p_rr2_cnd.opus",
      "name": "d4_p_rr2_cnd.opus",
      "url": "https://raw.githubusercontent.com/zulfikarbarbora-outl/weresax-opus-48/master/d4_p_rr2_cnd.opus",
      "size": 59210,
      "note": "d4",
      "midiNote": 62,
      "velocity": null,
      "dynamic": null,
      "roundRobin": 2
    },
    {
      "file": "d4_p_rr2_dnm.opus",
      "name": "d4_p_rr2_dnm.opus",
      "url": "https://raw.githubusercontent.com/zulfikarbarbora-outl/weresax-opus-48/master/d4_p_rr2_dnm.opus",
      "size": 56990,
      "note": "d4",
      "midiNote": 62,
      "velocity": null,
      "dynamic": null,
      "roundRobin": 2
    },
    {
      "file": "db2_f_rr1_cnd.opus",
      "name": "db2_f_rr1_cnd.opus",
      "url": "https://raw.githubusercontent.com/zulfikarbarbora-outl/weresax-opus-48/master/db2_f_rr1_cnd.opus",
      "size": 59760,
      "note": "db2",
      "midiNote": 37,
      "velocity": null,
      "dynamic": null,
      "roundRobin": 1
    },
    {
      "file": "db2_f_rr1_dnm.opus",
      "name": "db2_f_rr1_dnm.opus",
      "url": "https://raw.githubusercontent.com/zulfikarbarbora-outl/weresax-opus-48/master/db2_f_rr1_dnm.opus",
      "size": 66338,
      "note": "db2",
      "midiNote": 37,
      "velocity": null,
      "dynamic": null,
      "roundRobin": 1
    },
    {
      "file": "db2_f_rr2_cnd.opus",
      "name": "db2_f_rr2_cnd.opus",
      "url": "https://raw.githubusercontent.com/zulfikarbarbora-outl/weresax-opus-48/master/db2_f_rr2_cnd.opus",
      "size": 56198,
      "note": "db2",
      "midiNote": 37,
      "velocity": null,
      "dynamic": null,
      "roundRobin": 2
    },
    {
      "file": "db2_f_rr2_dnm.opus",
      "name": "db2_f_rr2_dnm.opus",
      "url": "https://raw.githubusercontent.com/zulfikarbarbora-outl/weresax-opus-48/master/db2_f_rr2_dnm.opus",
      "size": 61983,
      "note": "db2",
      "midiNote": 37,
      "velocity": null,
      "dynamic": null,
      "roundRobin": 2
    },
    {
      "file": "db2_p_rr1_cnd.opus",
      "name": "db2_p_rr1_cnd.opus",
      "url": "https://raw.githubusercontent.com/zulfikarbarbora-outl/weresax-opus-48/master/db2_p_rr1_cnd.opus",
      "size": 77836,
      "note": "db2",
      "midiNote": 37,
      "velocity": null,
      "dynamic": null,
      "roundRobin": 1
    },
    {
      "file": "db2_p_rr1_dnm.opus",
      "name": "db2_p_rr1_dnm.opus",
      "url": "https://raw.githubusercontent.com/zulfikarbarbora-outl/weresax-opus-48/master/db2_p_rr1_dnm.opus",
      "size": 62949,
      "note": "db2",
      "midiNote": 37,
      "velocity": null,
      "dynamic": null,
      "roundRobin": 1
    },
    {
      "file": "db2_p_rr2_cnd.opus",
      "name": "db2_p_rr2_cnd.opus",
      "url": "https://raw.githubusercontent.com/zulfikarbarbora-outl/weresax-opus-48/master/db2_p_rr2_cnd.opus",
      "size": 61777,
      "note": "db2",
      "midiNote": 37,
      "velocity": null,
      "dynamic": null,
      "roundRobin": 2
    },
    {
      "file": "db2_p_rr2_dnm.opus",
      "name": "db2_p_rr2_dnm.opus",
      "url": "https://raw.githubusercontent.com/zulfikarbarbora-outl/weresax-opus-48/master/db2_p_rr2_dnm.opus",
      "size": 56002,
      "note": "db2",
      "midiNote": 37,
      "velocity": null,
      "dynamic": null,
      "roundRobin": 2
    },
    {
      "file": "db3_f_rr1_cnd.opus",
      "name": "db3_f_rr1_cnd.opus",
      "url": "https://raw.githubusercontent.com/zulfikarbarbora-outl/weresax-opus-48/master/db3_f_rr1_cnd.opus",
      "size": 61244,
      "note": "db3",
      "midiNote": 49,
      "velocity": null,
      "dynamic": null,
      "roundRobin": 1
    },
    {
      "file": "db3_f_rr1_dnm.opus",
      "name": "db3_f_rr1_dnm.opus",
      "url": "https://raw.githubusercontent.com/zulfikarbarbora-outl/weresax-opus-48/master/db3_f_rr1_dnm.opus",
      "size": 60939,
      "note": "db3",
      "midiNote": 49,
      "velocity": null,
      "dynamic": null,
      "roundRobin": 1
    },
    {
      "file": "db3_f_rr2_cnd.opus",
      "name": "db3_f_rr2_cnd.opus",
      "url": "https://raw.githubusercontent.com/zulfikarbarbora-outl/weresax-opus-48/master/db3_f_rr2_cnd.opus",
      "size": 68113,
      "note": "db3",
      "midiNote": 49,
      "velocity": null,
      "dynamic": null,
      "roundRobin": 2
    },
    {
      "file": "db3_f_rr2_dnm.opus",
      "name": "db3_f_rr2_dnm.opus",
      "url": "https://raw.githubusercontent.com/zulfikarbarbora-outl/weresax-opus-48/master/db3_f_rr2_dnm.opus",
      "size": 68743,
      "note": "db3",
      "midiNote": 49,
      "velocity": null,
      "dynamic": null,
      "roundRobin": 2
    },
    {
      "file": "db3_p_rr1_cnd.opus",
      "name": "db3_p_rr1_cnd.opus",
      "url": "https://raw.githubusercontent.com/zulfikarbarbora-outl/weresax-opus-48/master/db3_p_rr1_cnd.opus",
      "size": 36309,
      "note": "db3",
      "midiNote": 49,
      "velocity": null,
      "dynamic": null,
      "roundRobin": 1
    },
    {
      "file": "db3_p_rr1_dnm.opus",
      "name": "db3_p_rr1_dnm.opus",
      "url": "https://raw.githubusercontent.com/zulfikarbarbora-outl/weresax-opus-48/master/db3_p_rr1_dnm.opus",
      "size": 35822,
      "note": "db3",
      "midiNote": 49,
      "velocity": null,
      "dynamic": null,
      "roundRobin": 1
    },
    {
      "file": "db3_p_rr2_cnd.opus",
      "name": "db3_p_rr2_cnd.opus",
      "url": "https://raw.githubusercontent.com/zulfikarbarbora-outl/weresax-opus-48/master/db3_p_rr2_cnd.opus",
      "size": 40295,
      "note": "db3",
      "midiNote": 49,
      "velocity": null,
      "dynamic": null,
      "roundRobin": 2
    },
    {
      "file": "db3_p_rr2_dnm.opus",
      "name": "db3_p_rr2_dnm.opus",
      "url": "https://raw.githubusercontent.com/zulfikarbarbora-outl/weresax-opus-48/master/db3_p_rr2_dnm.opus",
      "size": 40296,
      "note": "db3",
      "midiNote": 49,
      "velocity": null,
      "dynamic": null,
      "roundRobin": 2
    },
    {
      "file": "db4_f_rr1_cnd.opus",
      "name": "db4_f_rr1_cnd.opus",
      "url": "https://raw.githubusercontent.com/zulfikarbarbora-outl/weresax-opus-48/master/db4_f_rr1_cnd.opus",
      "size": 63655,
      "note": "db4",
      "midiNote": 61,
      "velocity": null,
      "dynamic": null,
      "roundRobin": 1
    },
    {
      "file": "db4_f_rr1_dnm.opus",
      "name": "db4_f_rr1_dnm.opus",
      "url": "https://raw.githubusercontent.com/zulfikarbarbora-outl/weresax-opus-48/master/db4_f_rr1_dnm.opus",
      "size": 63792,
      "note": "db4",
      "midiNote": 61,
      "velocity": null,
      "dynamic": null,
      "roundRobin": 1
    },
    {
      "file": "db4_f_rr2_cnd.opus",
      "name": "db4_f_rr2_cnd.opus",
      "url": "https://raw.githubusercontent.com/zulfikarbarbora-outl/weresax-opus-48/master/db4_f_rr2_cnd.opus",
      "size": 59671,
      "note": "db4",
      "midiNote": 61,
      "velocity": null,
      "dynamic": null,
      "roundRobin": 2
    },
    {
      "file": "db4_f_rr2_dnm.opus",
      "name": "db4_f_rr2_dnm.opus",
      "url": "https://raw.githubusercontent.com/zulfikarbarbora-outl/weresax-opus-48/master/db4_f_rr2_dnm.opus",
      "size": 60053,
      "note": "db4",
      "midiNote": 61,
      "velocity": null,
      "dynamic": null,
      "roundRobin": 2
    },
    {
      "file": "db4_p_rr1_cnd.opus",
      "name": "db4_p_rr1_cnd.opus",
      "url": "https://raw.githubusercontent.com/zulfikarbarbora-outl/weresax-opus-48/master/db4_p_rr1_cnd.opus",
      "size": 45227,
      "note": "db4",
      "midiNote": 61,
      "velocity": null,
      "dynamic": null,
      "roundRobin": 1
    },
    {
      "file": "db4_p_rr1_dnm.opus",
      "name": "db4_p_rr1_dnm.opus",
      "url": "https://raw.githubusercontent.com/zulfikarbarbora-outl/weresax-opus-48/master/db4_p_rr1_dnm.opus",
      "size": 48283,
      "note": "db4",
      "midiNote": 61,
      "velocity": null,
      "dynamic": null,
      "roundRobin": 1
    },
    {
      "file": "db4_p_rr2_cnd.opus",
      "name": "db4_p_rr2_cnd.opus",
      "url": "https://raw.githubusercontent.com/zulfikarbarbora-outl/weresax-opus-48/master/db4_p_rr2_cnd.opus",
      "size": 53687,
      "note": "db4",
      "midiNote": 61,
      "velocity": null,
      "dynamic": null,
      "roundRobin": 2
    },
    {
      "file": "db4_p_rr2_dnm.opus",
      "name": "db4_p_rr2_dnm.opus",
      "url": "https://raw.githubusercontent.com/zulfikarbarbora-outl/weresax-opus-48/master/db4_p_rr2_dnm.opus",
      "size": 58403,
      "note": "db4",
      "midiNote": 61,
      "velocity": null,
      "dynamic": null,
      "roundRobin": 2
    },
    {
      "file": "e2_f_rr1_cnd.opus",
      "name": "e2_f_rr1_cnd.opus",
      "url": "https://raw.githubusercontent.com/zulfikarbarbora-outl/weresax-opus-48/master/e2_f_rr1_cnd.opus",
      "size": 45627,
      "note": "e2",
      "midiNote": 40,
      "velocity": null,
      "dynamic": null,
      "roundRobin": 1
    },
    {
      "file": "e2_f_rr1_dnm.opus",
      "name": "e2_f_rr1_dnm.opus",
      "url": "https://raw.githubusercontent.com/zulfikarbarbora-outl/weresax-opus-48/master/e2_f_rr1_dnm.opus",
      "size": 51515,
      "note": "e2",
      "midiNote": 40,
      "velocity": null,
      "dynamic": null,
      "roundRobin": 1
    },
    {
      "file": "e2_f_rr2_cnd.opus",
      "name": "e2_f_rr2_cnd.opus",
      "url": "https://raw.githubusercontent.com/zulfikarbarbora-outl/weresax-opus-48/master/e2_f_rr2_cnd.opus",
      "size": 49237,
      "note": "e2",
      "midiNote": 40,
      "velocity": null,
      "dynamic": null,
      "roundRobin": 2
    },
    {
      "file": "e2_f_rr2_dnm.opus",
      "name": "e2_f_rr2_dnm.opus",
      "url": "https://raw.githubusercontent.com/zulfikarbarbora-outl/weresax-opus-48/master/e2_f_rr2_dnm.opus",
      "size": 54899,
      "note": "e2",
      "midiNote": 40,
      "velocity": null,
      "dynamic": null,
      "roundRobin": 2
    },
    {
      "file": "e2_p_rr1_cnd.opus",
      "name": "e2_p_rr1_cnd.opus",
      "url": "https://raw.githubusercontent.com/zulfikarbarbora-outl/weresax-opus-48/master/e2_p_rr1_cnd.opus",
      "size": 52887,
      "note": "e2",
      "midiNote": 40,
      "velocity": null,
      "dynamic": null,
      "roundRobin": 1
    },
    {
      "file": "e2_p_rr1_dnm.opus",
      "name": "e2_p_rr1_dnm.opus",
      "url": "https://raw.githubusercontent.com/zulfikarbarbora-outl/weresax-opus-48/master/e2_p_rr1_dnm.opus",
      "size": 58346,
      "note": "e2",
      "midiNote": 40,
      "velocity": null,
      "dynamic": null,
      "roundRobin": 1
    },
    {
      "file": "e2_p_rr2_cnd.opus",
      "name": "e2_p_rr2_cnd.opus",
      "url": "https://raw.githubusercontent.com/zulfikarbarbora-outl/weresax-opus-48/master/e2_p_rr2_cnd.opus",
      "size": 54021,
      "note": "e2",
      "midiNote": 40,
      "velocity": null,
      "dynamic": null,
      "roundRobin": 2
    },
    {
      "file": "e2_p_rr2_dnm.opus",
      "name": "e2_p_rr2_dnm.opus",
      "url": "https://raw.githubusercontent.com/zulfikarbarbora-outl/weresax-opus-48/master/e2_p_rr2_dnm.opus",
      "size": 67853,
      "note": "e2",
      "midiNote": 40,
      "velocity": null,
      "dynamic": null,
      "roundRobin": 2
    },
    {
      "file": "e3_f_rr1_cnd.opus",
      "name": "e3_f_rr1_cnd.opus",
      "url": "https://raw.githubusercontent.com/zulfikarbarbora-outl/weresax-opus-48/master/e3_f_rr1_cnd.opus",
      "size": 61300,
      "note": "e3",
      "midiNote": 52,
      "velocity": null,
      "dynamic": null,
      "roundRobin": 1
    },
    {
      "file": "e3_f_rr1_dnm.opus",
      "name": "e3_f_rr1_dnm.opus",
      "url": "https://raw.githubusercontent.com/zulfikarbarbora-outl/weresax-opus-48/master/e3_f_rr1_dnm.opus",
      "size": 63271,
      "note": "e3",
      "midiNote": 52,
      "velocity": null,
      "dynamic": null,
      "roundRobin": 1
    },
    {
      "file": "e3_f_rr2_cnd.opus",
      "name": "e3_f_rr2_cnd.opus",
      "url": "https://raw.githubusercontent.com/zulfikarbarbora-outl/weresax-opus-48/master/e3_f_rr2_cnd.opus",
      "size": 64877,
      "note": "e3",
      "midiNote": 52,
      "velocity": null,
      "dynamic": null,
      "roundRobin": 2
    },
    {
      "file": "e3_f_rr2_dnm.opus",
      "name": "e3_f_rr2_dnm.opus",
      "url": "https://raw.githubusercontent.com/zulfikarbarbora-outl/weresax-opus-48/master/e3_f_rr2_dnm.opus",
      "size": 67078,
      "note": "e3",
      "midiNote": 52,
      "velocity": null,
      "dynamic": null,
      "roundRobin": 2
    },
    {
      "file": "e3_p_rr1_cnd.opus",
      "name": "e3_p_rr1_cnd.opus",
      "url": "https://raw.githubusercontent.com/zulfikarbarbora-outl/weresax-opus-48/master/e3_p_rr1_cnd.opus",
      "size": 38555,
      "note": "e3",
      "midiNote": 52,
      "velocity": null,
      "dynamic": null,
      "roundRobin": 1
    },
    {
      "file": "e3_p_rr1_dnm.opus",
      "name": "e3_p_rr1_dnm.opus",
      "url": "https://raw.githubusercontent.com/zulfikarbarbora-outl/weresax-opus-48/master/e3_p_rr1_dnm.opus",
      "size": 41576,
      "note": "e3",
      "midiNote": 52,
      "velocity": null,
      "dynamic": null,
      "roundRobin": 1
    },
    {
      "file": "e3_p_rr2_cnd.opus",
      "name": "e3_p_rr2_cnd.opus",
      "url": "https://raw.githubusercontent.com/zulfikarbarbora-outl/weresax-opus-48/master/e3_p_rr2_cnd.opus",
      "size": 42878,
      "note": "e3",
      "midiNote": 52,
      "velocity": null,
      "dynamic": null,
      "roundRobin": 2
    },
    {
      "file": "e3_p_rr2_dnm.opus",
      "name": "e3_p_rr2_dnm.opus",
      "url": "https://raw.githubusercontent.com/zulfikarbarbora-outl/weresax-opus-48/master/e3_p_rr2_dnm.opus",
      "size": 42028,
      "note": "e3",
      "midiNote": 52,
      "velocity": null,
      "dynamic": null,
      "roundRobin": 2
    },
    {
      "file": "e4_f_rr1_cnd.opus",
      "name": "e4_f_rr1_cnd.opus",
      "url": "https://raw.githubusercontent.com/zulfikarbarbora-outl/weresax-opus-48/master/e4_f_rr1_cnd.opus",
      "size": 58309,
      "note": "e4",
      "midiNote": 64,
      "velocity": null,
      "dynamic": null,
      "roundRobin": 1
    },
    {
      "file": "e4_f_rr1_dnm.opus",
      "name": "e4_f_rr1_dnm.opus",
      "url": "https://raw.githubusercontent.com/zulfikarbarbora-outl/weresax-opus-48/master/e4_f_rr1_dnm.opus",
      "size": 56970,
      "note": "e4",
      "midiNote": 64,
      "velocity": null,
      "dynamic": null,
      "roundRobin": 1
    },
    {
      "file": "e4_f_rr2_cnd.opus",
      "name": "e4_f_rr2_cnd.opus",
      "url": "https://raw.githubusercontent.com/zulfikarbarbora-outl/weresax-opus-48/master/e4_f_rr2_cnd.opus",
      "size": 54202,
      "note": "e4",
      "midiNote": 64,
      "velocity": null,
      "dynamic": null,
      "roundRobin": 2
    },
    {
      "file": "e4_f_rr2_dnm.opus",
      "name": "e4_f_rr2_dnm.opus",
      "url": "https://raw.githubusercontent.com/zulfikarbarbora-outl/weresax-opus-48/master/e4_f_rr2_dnm.opus",
      "size": 54332,
      "note": "e4",
      "midiNote": 64,
      "velocity": null,
      "dynamic": null,
      "roundRobin": 2
    },
    {
      "file": "e4_p_rr1_cnd.opus",
      "name": "e4_p_rr1_cnd.opus",
      "url": "https://raw.githubusercontent.com/zulfikarbarbora-outl/weresax-opus-48/master/e4_p_rr1_cnd.opus",
      "size": 51481,
      "note": "e4",
      "midiNote": 64,
      "velocity": null,
      "dynamic": null,
      "roundRobin": 1
    },
    {
      "file": "e4_p_rr1_dnm.opus",
      "name": "e4_p_rr1_dnm.opus",
      "url": "https://raw.githubusercontent.com/zulfikarbarbora-outl/weresax-opus-48/master/e4_p_rr1_dnm.opus",
      "size": 48475,
      "note": "e4",
      "midiNote": 64,
      "velocity": null,
      "dynamic": null,
      "roundRobin": 1
    },
    {
      "file": "e4_p_rr2_cnd.opus",
      "name": "e4_p_rr2_cnd.opus",
      "url": "https://raw.githubusercontent.com/zulfikarbarbora-outl/weresax-opus-48/master/e4_p_rr2_cnd.opus",
      "size": 50215,
      "note": "e4",
      "midiNote": 64,
      "velocity": null,
      "dynamic": null,
      "roundRobin": 2
    },
    {
      "file": "e4_p_rr2_dnm.opus",
      "name": "e4_p_rr2_dnm.opus",
      "url": "https://raw.githubusercontent.com/zulfikarbarbora-outl/weresax-opus-48/master/e4_p_rr2_dnm.opus",
      "size": 50598,
      "note": "e4",
      "midiNote": 64,
      "velocity": null,
      "dynamic": null,
      "roundRobin": 2
    },
    {
      "file": "eb2_f_rr1_cnd.opus",
      "name": "eb2_f_rr1_cnd.opus",
      "url": "https://raw.githubusercontent.com/zulfikarbarbora-outl/weresax-opus-48/master/eb2_f_rr1_cnd.opus",
      "size": 49732,
      "note": "eb2",
      "midiNote": 39,
      "velocity": null,
      "dynamic": null,
      "roundRobin": 1
    },
    {
      "file": "eb2_f_rr1_dnm.opus",
      "name": "eb2_f_rr1_dnm.opus",
      "url": "https://raw.githubusercontent.com/zulfikarbarbora-outl/weresax-opus-48/master/eb2_f_rr1_dnm.opus",
      "size": 60682,
      "note": "eb2",
      "midiNote": 39,
      "velocity": null,
      "dynamic": null,
      "roundRobin": 1
    },
    {
      "file": "eb2_f_rr2_cnd.opus",
      "name": "eb2_f_rr2_cnd.opus",
      "url": "https://raw.githubusercontent.com/zulfikarbarbora-outl/weresax-opus-48/master/eb2_f_rr2_cnd.opus",
      "size": 53901,
      "note": "eb2",
      "midiNote": 39,
      "velocity": null,
      "dynamic": null,
      "roundRobin": 2
    },
    {
      "file": "eb2_f_rr2_dnm.opus",
      "name": "eb2_f_rr2_dnm.opus",
      "url": "https://raw.githubusercontent.com/zulfikarbarbora-outl/weresax-opus-48/master/eb2_f_rr2_dnm.opus",
      "size": 61865,
      "note": "eb2",
      "midiNote": 39,
      "velocity": null,
      "dynamic": null,
      "roundRobin": 2
    },
    {
      "file": "eb2_p_rr1_cnd.opus",
      "name": "eb2_p_rr1_cnd.opus",
      "url": "https://raw.githubusercontent.com/zulfikarbarbora-outl/weresax-opus-48/master/eb2_p_rr1_cnd.opus",
      "size": 49141,
      "note": "eb2",
      "midiNote": 39,
      "velocity": null,
      "dynamic": null,
      "roundRobin": 1
    },
    {
      "file": "eb2_p_rr1_dnm.opus",
      "name": "eb2_p_rr1_dnm.opus",
      "url": "https://raw.githubusercontent.com/zulfikarbarbora-outl/weresax-opus-48/master/eb2_p_rr1_dnm.opus",
      "size": 55223,
      "note": "eb2",
      "midiNote": 39,
      "velocity": null,
      "dynamic": null,
      "roundRobin": 1
    },
    {
      "file": "eb2_p_rr2_cnd.opus",
      "name": "eb2_p_rr2_cnd.opus",
      "url": "https://raw.githubusercontent.com/zulfikarbarbora-outl/weresax-opus-48/master/eb2_p_rr2_cnd.opus",
      "size": 49483,
      "note": "eb2",
      "midiNote": 39,
      "velocity": null,
      "dynamic": null,
      "roundRobin": 2
    },
    {
      "file": "eb2_p_rr2_dnm.opus",
      "name": "eb2_p_rr2_dnm.opus",
      "url": "https://raw.githubusercontent.com/zulfikarbarbora-outl/weresax-opus-48/master/eb2_p_rr2_dnm.opus",
      "size": 50618,
      "note": "eb2",
      "midiNote": 39,
      "velocity": null,
      "dynamic": null,
      "roundRobin": 2
    },
    {
      "file": "eb3_f_rr1_cnd.opus",
      "name": "eb3_f_rr1_cnd.opus",
      "url": "https://raw.githubusercontent.com/zulfikarbarbora-outl/weresax-opus-48/master/eb3_f_rr1_cnd.opus",
      "size": 51482,
      "note": "eb3",
      "midiNote": 51,
      "velocity": null,
      "dynamic": null,
      "roundRobin": 1
    },
    {
      "file": "eb3_f_rr1_dnm.opus",
      "name": "eb3_f_rr1_dnm.opus",
      "url": "https://raw.githubusercontent.com/zulfikarbarbora-outl/weresax-opus-48/master/eb3_f_rr1_dnm.opus",
      "size": 51056,
      "note": "eb3",
      "midiNote": 51,
      "velocity": null,
      "dynamic": null,
      "roundRobin": 1
    },
    {
      "file": "eb3_f_rr2_cnd.opus",
      "name": "eb3_f_rr2_cnd.opus",
      "url": "https://raw.githubusercontent.com/zulfikarbarbora-outl/weresax-opus-48/master/eb3_f_rr2_cnd.opus",
      "size": 47714,
      "note": "eb3",
      "midiNote": 51,
      "velocity": null,
      "dynamic": null,
      "roundRobin": 2
    },
    {
      "file": "eb3_f_rr2_dnm.opus",
      "name": "eb3_f_rr2_dnm.opus",
      "url": "https://raw.githubusercontent.com/zulfikarbarbora-outl/weresax-opus-48/master/eb3_f_rr2_dnm.opus",
      "size": 46561,
      "note": "eb3",
      "midiNote": 51,
      "velocity": null,
      "dynamic": null,
      "roundRobin": 2
    },
    {
      "file": "eb3_p_rr1_cnd.opus",
      "name": "eb3_p_rr1_cnd.opus",
      "url": "https://raw.githubusercontent.com/zulfikarbarbora-outl/weresax-opus-48/master/eb3_p_rr1_cnd.opus",
      "size": 49580,
      "note": "eb3",
      "midiNote": 51,
      "velocity": null,
      "dynamic": null,
      "roundRobin": 1
    },
    {
      "file": "eb3_p_rr1_dnm.opus",
      "name": "eb3_p_rr1_dnm.opus",
      "url": "https://raw.githubusercontent.com/zulfikarbarbora-outl/weresax-opus-48/master/eb3_p_rr1_dnm.opus",
      "size": 50840,
      "note": "eb3",
      "midiNote": 51,
      "velocity": null,
      "dynamic": null,
      "roundRobin": 1
    },
    {
      "file": "eb3_p_rr2_cnd.opus",
      "name": "eb3_p_rr2_cnd.opus",
      "url": "https://raw.githubusercontent.com/zulfikarbarbora-outl/weresax-opus-48/master/eb3_p_rr2_cnd.opus",
      "size": 53119,
      "note": "eb3",
      "midiNote": 51,
      "velocity": null,
      "dynamic": null,
      "roundRobin": 2
    },
    {
      "file": "eb3_p_rr2_dnm.opus",
      "name": "eb3_p_rr2_dnm.opus",
      "url": "https://raw.githubusercontent.com/zulfikarbarbora-outl/weresax-opus-48/master/eb3_p_rr2_dnm.opus",
      "size": 54616,
      "note": "eb3",
      "midiNote": 51,
      "velocity": null,
      "dynamic": null,
      "roundRobin": 2
    },
    {
      "file": "eb4_f_rr1_cnd.opus",
      "name": "eb4_f_rr1_cnd.opus",
      "url": "https://raw.githubusercontent.com/zulfikarbarbora-outl/weresax-opus-48/master/eb4_f_rr1_cnd.opus",
      "size": 54166,
      "note": "eb4",
      "midiNote": 63,
      "velocity": null,
      "dynamic": null,
      "roundRobin": 1
    },
    {
      "file": "eb4_f_rr1_dnm.opus",
      "name": "eb4_f_rr1_dnm.opus",
      "url": "https://raw.githubusercontent.com/zulfikarbarbora-outl/weresax-opus-48/master/eb4_f_rr1_dnm.opus",
      "size": 53349,
      "note": "eb4",
      "midiNote": 63,
      "velocity": null,
      "dynamic": null,
      "roundRobin": 1
    },
    {
      "file": "eb4_f_rr2_cnd.opus",
      "name": "eb4_f_rr2_cnd.opus",
      "url": "https://raw.githubusercontent.com/zulfikarbarbora-outl/weresax-opus-48/master/eb4_f_rr2_cnd.opus",
      "size": 55214,
      "note": "eb4",
      "midiNote": 63,
      "velocity": null,
      "dynamic": null,
      "roundRobin": 2
    },
    {
      "file": "eb4_f_rr2_dnm.opus",
      "name": "eb4_f_rr2_dnm.opus",
      "url": "https://raw.githubusercontent.com/zulfikarbarbora-outl/weresax-opus-48/master/eb4_f_rr2_dnm.opus",
      "size": 53816,
      "note": "eb4",
      "midiNote": 63,
      "velocity": null,
      "dynamic": null,
      "roundRobin": 2
    },
    {
      "file": "eb4_p_rr1_cnd.opus",
      "name": "eb4_p_rr1_cnd.opus",
      "url": "https://raw.githubusercontent.com/zulfikarbarbora-outl/weresax-opus-48/master/eb4_p_rr1_cnd.opus",
      "size": 48780,
      "note": "eb4",
      "midiNote": 63,
      "velocity": null,
      "dynamic": null,
      "roundRobin": 1
    },
    {
      "file": "eb4_p_rr1_dnm.opus",
      "name": "eb4_p_rr1_dnm.opus",
      "url": "https://raw.githubusercontent.com/zulfikarbarbora-outl/weresax-opus-48/master/eb4_p_rr1_dnm.opus",
      "size": 46264,
      "note": "eb4",
      "midiNote": 63,
      "velocity": null,
      "dynamic": null,
      "roundRobin": 1
    },
    {
      "file": "eb4_p_rr2_cnd.opus",
      "name": "eb4_p_rr2_cnd.opus",
      "url": "https://raw.githubusercontent.com/zulfikarbarbora-outl/weresax-opus-48/master/eb4_p_rr2_cnd.opus",
      "size": 51937,
      "note": "eb4",
      "midiNote": 63,
      "velocity": null,
      "dynamic": null,
      "roundRobin": 2
    },
    {
      "file": "eb4_p_rr2_dnm.opus",
      "name": "eb4_p_rr2_dnm.opus",
      "url": "https://raw.githubusercontent.com/zulfikarbarbora-outl/weresax-opus-48/master/eb4_p_rr2_dnm.opus",
      "size": 51100,
      "note": "eb4",
      "midiNote": 63,
      "velocity": null,
      "dynamic": null,
      "roundRobin": 2
    },
    {
      "file": "f2_f_rr1_cnd.opus",
      "name": "f2_f_rr1_cnd.opus",
      "url": "https://raw.githubusercontent.com/zulfikarbarbora-outl/weresax-opus-48/master/f2_f_rr1_cnd.opus",
      "size": 41651,
      "note": "f2",
      "midiNote": 41,
      "velocity": null,
      "dynamic": null,
      "roundRobin": 1
    },
    {
      "file": "f2_f_rr1_dnm.opus",
      "name": "f2_f_rr1_dnm.opus",
      "url": "https://raw.githubusercontent.com/zulfikarbarbora-outl/weresax-opus-48/master/f2_f_rr1_dnm.opus",
      "size": 49670,
      "note": "f2",
      "midiNote": 41,
      "velocity": null,
      "dynamic": null,
      "roundRobin": 1
    },
    {
      "file": "f2_f_rr2_cnd.opus",
      "name": "f2_f_rr2_cnd.opus",
      "url": "https://raw.githubusercontent.com/zulfikarbarbora-outl/weresax-opus-48/master/f2_f_rr2_cnd.opus",
      "size": 42068,
      "note": "f2",
      "midiNote": 41,
      "velocity": null,
      "dynamic": null,
      "roundRobin": 2
    },
    {
      "file": "f2_f_rr2_dnm.opus",
      "name": "f2_f_rr2_dnm.opus",
      "url": "https://raw.githubusercontent.com/zulfikarbarbora-outl/weresax-opus-48/master/f2_f_rr2_dnm.opus",
      "size": 46732,
      "note": "f2",
      "midiNote": 41,
      "velocity": null,
      "dynamic": null,
      "roundRobin": 2
    },
    {
      "file": "f2_p_rr1_cnd.opus",
      "name": "f2_p_rr1_cnd.opus",
      "url": "https://raw.githubusercontent.com/zulfikarbarbora-outl/weresax-opus-48/master/f2_p_rr1_cnd.opus",
      "size": 56213,
      "note": "f2",
      "midiNote": 41,
      "velocity": null,
      "dynamic": null,
      "roundRobin": 1
    },
    {
      "file": "f2_p_rr1_dnm.opus",
      "name": "f2_p_rr1_dnm.opus",
      "url": "https://raw.githubusercontent.com/zulfikarbarbora-outl/weresax-opus-48/master/f2_p_rr1_dnm.opus",
      "size": 53676,
      "note": "f2",
      "midiNote": 41,
      "velocity": null,
      "dynamic": null,
      "roundRobin": 1
    },
    {
      "file": "f2_p_rr2_cnd.opus",
      "name": "f2_p_rr2_cnd.opus",
      "url": "https://raw.githubusercontent.com/zulfikarbarbora-outl/weresax-opus-48/master/f2_p_rr2_cnd.opus",
      "size": 48339,
      "note": "f2",
      "midiNote": 41,
      "velocity": null,
      "dynamic": null,
      "roundRobin": 2
    },
    {
      "file": "f2_p_rr2_dnm.opus",
      "name": "f2_p_rr2_dnm.opus",
      "url": "https://raw.githubusercontent.com/zulfikarbarbora-outl/weresax-opus-48/master/f2_p_rr2_dnm.opus",
      "size": 47331,
      "note": "f2",
      "midiNote": 41,
      "velocity": null,
      "dynamic": null,
      "roundRobin": 2
    },
    {
      "file": "f3_f_rr1_cnd.opus",
      "name": "f3_f_rr1_cnd.opus",
      "url": "https://raw.githubusercontent.com/zulfikarbarbora-outl/weresax-opus-48/master/f3_f_rr1_cnd.opus",
      "size": 53641,
      "note": "f3",
      "midiNote": 53,
      "velocity": null,
      "dynamic": null,
      "roundRobin": 1
    },
    {
      "file": "f3_f_rr1_dnm.opus",
      "name": "f3_f_rr1_dnm.opus",
      "url": "https://raw.githubusercontent.com/zulfikarbarbora-outl/weresax-opus-48/master/f3_f_rr1_dnm.opus",
      "size": 64964,
      "note": "f3",
      "midiNote": 53,
      "velocity": null,
      "dynamic": null,
      "roundRobin": 1
    },
    {
      "file": "f3_f_rr2_cnd.opus",
      "name": "f3_f_rr2_cnd.opus",
      "url": "https://raw.githubusercontent.com/zulfikarbarbora-outl/weresax-opus-48/master/f3_f_rr2_cnd.opus",
      "size": 67876,
      "note": "f3",
      "midiNote": 53,
      "velocity": null,
      "dynamic": null,
      "roundRobin": 2
    },
    {
      "file": "f3_f_rr2_dnm.opus",
      "name": "f3_f_rr2_dnm.opus",
      "url": "https://raw.githubusercontent.com/zulfikarbarbora-outl/weresax-opus-48/master/f3_f_rr2_dnm.opus",
      "size": 72900,
      "note": "f3",
      "midiNote": 53,
      "velocity": null,
      "dynamic": null,
      "roundRobin": 2
    },
    {
      "file": "f3_p_rr1_cnd.opus",
      "name": "f3_p_rr1_cnd.opus",
      "url": "https://raw.githubusercontent.com/zulfikarbarbora-outl/weresax-opus-48/master/f3_p_rr1_cnd.opus",
      "size": 48050,
      "note": "f3",
      "midiNote": 53,
      "velocity": null,
      "dynamic": null,
      "roundRobin": 1
    },
    {
      "file": "f3_p_rr1_dnm.opus",
      "name": "f3_p_rr1_dnm.opus",
      "url": "https://raw.githubusercontent.com/zulfikarbarbora-outl/weresax-opus-48/master/f3_p_rr1_dnm.opus",
      "size": 50171,
      "note": "f3",
      "midiNote": 53,
      "velocity": null,
      "dynamic": null,
      "roundRobin": 1
    },
    {
      "file": "f3_p_rr2_cnd.opus",
      "name": "f3_p_rr2_cnd.opus",
      "url": "https://raw.githubusercontent.com/zulfikarbarbora-outl/weresax-opus-48/master/f3_p_rr2_cnd.opus",
      "size": 49932,
      "note": "f3",
      "midiNote": 53,
      "velocity": null,
      "dynamic": null,
      "roundRobin": 2
    },
    {
      "file": "f3_p_rr2_dnm.opus",
      "name": "f3_p_rr2_dnm.opus",
      "url": "https://raw.githubusercontent.com/zulfikarbarbora-outl/weresax-opus-48/master/f3_p_rr2_dnm.opus",
      "size": 52723,
      "note": "f3",
      "midiNote": 53,
      "velocity": null,
      "dynamic": null,
      "roundRobin": 2
    },
    {
      "file": "f4_f_rr1_cnd.opus",
      "name": "f4_f_rr1_cnd.opus",
      "url": "https://raw.githubusercontent.com/zulfikarbarbora-outl/weresax-opus-48/master/f4_f_rr1_cnd.opus",
      "size": 62152,
      "note": "f4",
      "midiNote": 65,
      "velocity": null,
      "dynamic": null,
      "roundRobin": 1
    },
    {
      "file": "f4_f_rr1_dnm.opus",
      "name": "f4_f_rr1_dnm.opus",
      "url": "https://raw.githubusercontent.com/zulfikarbarbora-outl/weresax-opus-48/master/f4_f_rr1_dnm.opus",
      "size": 63274,
      "note": "f4",
      "midiNote": 65,
      "velocity": null,
      "dynamic": null,
      "roundRobin": 1
    },
    {
      "file": "f4_f_rr2_cnd.opus",
      "name": "f4_f_rr2_cnd.opus",
      "url": "https://raw.githubusercontent.com/zulfikarbarbora-outl/weresax-opus-48/master/f4_f_rr2_cnd.opus",
      "size": 62200,
      "note": "f4",
      "midiNote": 65,
      "velocity": null,
      "dynamic": null,
      "roundRobin": 2
    },
    {
      "file": "f4_f_rr2_dnm.opus",
      "name": "f4_f_rr2_dnm.opus",
      "url": "https://raw.githubusercontent.com/zulfikarbarbora-outl/weresax-opus-48/master/f4_f_rr2_dnm.opus",
      "size": 62795,
      "note": "f4",
      "midiNote": 65,
      "velocity": null,
      "dynamic": null,
      "roundRobin": 2
    },
    {
      "file": "f4_p_rr1_cnd.opus",
      "name": "f4_p_rr1_cnd.opus",
      "url": "https://raw.githubusercontent.com/zulfikarbarbora-outl/weresax-opus-48/master/f4_p_rr1_cnd.opus",
      "size": 55084,
      "note": "f4",
      "midiNote": 65,
      "velocity": null,
      "dynamic": null,
      "roundRobin": 1
    },
    {
      "file": "f4_p_rr1_dnm.opus",
      "name": "f4_p_rr1_dnm.opus",
      "url": "https://raw.githubusercontent.com/zulfikarbarbora-outl/weresax-opus-48/master/f4_p_rr1_dnm.opus",
      "size": 60239,
      "note": "f4",
      "midiNote": 65,
      "velocity": null,
      "dynamic": null,
      "roundRobin": 1
    },
    {
      "file": "f4_p_rr2_cnd.opus",
      "name": "f4_p_rr2_cnd.opus",
      "url": "https://raw.githubusercontent.com/zulfikarbarbora-outl/weresax-opus-48/master/f4_p_rr2_cnd.opus",
      "size": 59763,
      "note": "f4",
      "midiNote": 65,
      "velocity": null,
      "dynamic": null,
      "roundRobin": 2
    },
    {
      "file": "f4_p_rr2_dnm.opus",
      "name": "f4_p_rr2_dnm.opus",
      "url": "https://raw.githubusercontent.com/zulfikarbarbora-outl/weresax-opus-48/master/f4_p_rr2_dnm.opus",
      "size": 63003,
      "note": "f4",
      "midiNote": 65,
      "velocity": null,
      "dynamic": null,
      "roundRobin": 2
    },
    {
      "file": "g2_f_rr1_cnd.opus",
      "name": "g2_f_rr1_cnd.opus",
      "url": "https://raw.githubusercontent.com/zulfikarbarbora-outl/weresax-opus-48/master/g2_f_rr1_cnd.opus",
      "size": 42373,
      "note": "g2",
      "midiNote": 43,
      "velocity": null,
      "dynamic": null,
      "roundRobin": 1
    },
    {
      "file": "g2_f_rr1_dnm.opus",
      "name": "g2_f_rr1_dnm.opus",
      "url": "https://raw.githubusercontent.com/zulfikarbarbora-outl/weresax-opus-48/master/g2_f_rr1_dnm.opus",
      "size": 40547,
      "note": "g2",
      "midiNote": 43,
      "velocity": null,
      "dynamic": null,
      "roundRobin": 1
    },
    {
      "file": "g2_f_rr2_cnd.opus",
      "name": "g2_f_rr2_cnd.opus",
      "url": "https://raw.githubusercontent.com/zulfikarbarbora-outl/weresax-opus-48/master/g2_f_rr2_cnd.opus",
      "size": 38393,
      "note": "g2",
      "midiNote": 43,
      "velocity": null,
      "dynamic": null,
      "roundRobin": 2
    },
    {
      "file": "g2_f_rr2_dnm.opus",
      "name": "g2_f_rr2_dnm.opus",
      "url": "https://raw.githubusercontent.com/zulfikarbarbora-outl/weresax-opus-48/master/g2_f_rr2_dnm.opus",
      "size": 40433,
      "note": "g2",
      "midiNote": 43,
      "velocity": null,
      "dynamic": null,
      "roundRobin": 2
    },
    {
      "file": "g2_p_rr1_cnd.opus",
      "name": "g2_p_rr1_cnd.opus",
      "url": "https://raw.githubusercontent.com/zulfikarbarbora-outl/weresax-opus-48/master/g2_p_rr1_cnd.opus",
      "size": 43168,
      "note": "g2",
      "midiNote": 43,
      "velocity": null,
      "dynamic": null,
      "roundRobin": 1
    },
    {
      "file": "g2_p_rr1_dnm.opus",
      "name": "g2_p_rr1_dnm.opus",
      "url": "https://raw.githubusercontent.com/zulfikarbarbora-outl/weresax-opus-48/master/g2_p_rr1_dnm.opus",
      "size": 43700,
      "note": "g2",
      "midiNote": 43,
      "velocity": null,
      "dynamic": null,
      "roundRobin": 1
    },
    {
      "file": "g2_p_rr2_cnd.opus",
      "name": "g2_p_rr2_cnd.opus",
      "url": "https://raw.githubusercontent.com/zulfikarbarbora-outl/weresax-opus-48/master/g2_p_rr2_cnd.opus",
      "size": 39738,
      "note": "g2",
      "midiNote": 43,
      "velocity": null,
      "dynamic": null,
      "roundRobin": 2
    },
    {
      "file": "g2_p_rr2_dnm.opus",
      "name": "g2_p_rr2_dnm.opus",
      "url": "https://raw.githubusercontent.com/zulfikarbarbora-outl/weresax-opus-48/master/g2_p_rr2_dnm.opus",
      "size": 40515,
      "note": "g2",
      "midiNote": 43,
      "velocity": null,
      "dynamic": null,
      "roundRobin": 2
    },
    {
      "file": "g3_f_rr1_cnd.opus",
      "name": "g3_f_rr1_cnd.opus",
      "url": "https://raw.githubusercontent.com/zulfikarbarbora-outl/weresax-opus-48/master/g3_f_rr1_cnd.opus",
      "size": 56645,
      "note": "g3",
      "midiNote": 55,
      "velocity": null,
      "dynamic": null,
      "roundRobin": 1
    },
    {
      "file": "g3_f_rr1_dnm.opus",
      "name": "g3_f_rr1_dnm.opus",
      "url": "https://raw.githubusercontent.com/zulfikarbarbora-outl/weresax-opus-48/master/g3_f_rr1_dnm.opus",
      "size": 60302,
      "note": "g3",
      "midiNote": 55,
      "velocity": null,
      "dynamic": null,
      "roundRobin": 1
    },
    {
      "file": "g3_f_rr2_cnd.opus",
      "name": "g3_f_rr2_cnd.opus",
      "url": "https://raw.githubusercontent.com/zulfikarbarbora-outl/weresax-opus-48/master/g3_f_rr2_cnd.opus",
      "size": 54403,
      "note": "g3",
      "midiNote": 55,
      "velocity": null,
      "dynamic": null,
      "roundRobin": 2
    },
    {
      "file": "g3_f_rr2_dnm.opus",
      "name": "g3_f_rr2_dnm.opus",
      "url": "https://raw.githubusercontent.com/zulfikarbarbora-outl/weresax-opus-48/master/g3_f_rr2_dnm.opus",
      "size": 61034,
      "note": "g3",
      "midiNote": 55,
      "velocity": null,
      "dynamic": null,
      "roundRobin": 2
    },
    {
      "file": "g3_p_rr1_cnd.opus",
      "name": "g3_p_rr1_cnd.opus",
      "url": "https://raw.githubusercontent.com/zulfikarbarbora-outl/weresax-opus-48/master/g3_p_rr1_cnd.opus",
      "size": 47947,
      "note": "g3",
      "midiNote": 55,
      "velocity": null,
      "dynamic": null,
      "roundRobin": 1
    },
    {
      "file": "g3_p_rr1_dnm.opus",
      "name": "g3_p_rr1_dnm.opus",
      "url": "https://raw.githubusercontent.com/zulfikarbarbora-outl/weresax-opus-48/master/g3_p_rr1_dnm.opus",
      "size": 52479,
      "note": "g3",
      "midiNote": 55,
      "velocity": null,
      "dynamic": null,
      "roundRobin": 1
    },
    {
      "file": "g3_p_rr2_cnd.opus",
      "name": "g3_p_rr2_cnd.opus",
      "url": "https://raw.githubusercontent.com/zulfikarbarbora-outl/weresax-opus-48/master/g3_p_rr2_cnd.opus",
      "size": 46923,
      "note": "g3",
      "midiNote": 55,
      "velocity": null,
      "dynamic": null,
      "roundRobin": 2
    },
    {
      "file": "g3_p_rr2_dnm.opus",
      "name": "g3_p_rr2_dnm.opus",
      "url": "https://raw.githubusercontent.com/zulfikarbarbora-outl/weresax-opus-48/master/g3_p_rr2_dnm.opus",
      "size": 52941,
      "note": "g3",
      "midiNote": 55,
      "velocity": null,
      "dynamic": null,
      "roundRobin": 2
    },
    {
      "file": "g4_f_rr1_cnd.opus",
      "name": "g4_f_rr1_cnd.opus",
      "url": "https://raw.githubusercontent.com/zulfikarbarbora-outl/weresax-opus-48/master/g4_f_rr1_cnd.opus",
      "size": 71921,
      "note": "g4",
      "midiNote": 67,
      "velocity": null,
      "dynamic": null,
      "roundRobin": 1
    },
    {
      "file": "g4_f_rr1_dnm.opus",
      "name": "g4_f_rr1_dnm.opus",
      "url": "https://raw.githubusercontent.com/zulfikarbarbora-outl/weresax-opus-48/master/g4_f_rr1_dnm.opus",
      "size": 70222,
      "note": "g4",
      "midiNote": 67,
      "velocity": null,
      "dynamic": null,
      "roundRobin": 1
    },
    {
      "file": "g4_f_rr2_cnd.opus",
      "name": "g4_f_rr2_cnd.opus",
      "url": "https://raw.githubusercontent.com/zulfikarbarbora-outl/weresax-opus-48/master/g4_f_rr2_cnd.opus",
      "size": 80042,
      "note": "g4",
      "midiNote": 67,
      "velocity": null,
      "dynamic": null,
      "roundRobin": 2
    },
    {
      "file": "g4_f_rr2_dnm.opus",
      "name": "g4_f_rr2_dnm.opus",
      "url": "https://raw.githubusercontent.com/zulfikarbarbora-outl/weresax-opus-48/master/g4_f_rr2_dnm.opus",
      "size": 77693,
      "note": "g4",
      "midiNote": 67,
      "velocity": null,
      "dynamic": null,
      "roundRobin": 2
    },
    {
      "file": "g4_p_rr1_cnd.opus",
      "name": "g4_p_rr1_cnd.opus",
      "url": "https://raw.githubusercontent.com/zulfikarbarbora-outl/weresax-opus-48/master/g4_p_rr1_cnd.opus",
      "size": 60878,
      "note": "g4",
      "midiNote": 67,
      "velocity": null,
      "dynamic": null,
      "roundRobin": 1
    },
    {
      "file": "g4_p_rr1_dnm.opus",
      "name": "g4_p_rr1_dnm.opus",
      "url": "https://raw.githubusercontent.com/zulfikarbarbora-outl/weresax-opus-48/master/g4_p_rr1_dnm.opus",
      "size": 62697,
      "note": "g4",
      "midiNote": 67,
      "velocity": null,
      "dynamic": null,
      "roundRobin": 1
    },
    {
      "file": "g4_p_rr2_cnd.opus",
      "name": "g4_p_rr2_cnd.opus",
      "url": "https://raw.githubusercontent.com/zulfikarbarbora-outl/weresax-opus-48/master/g4_p_rr2_cnd.opus",
      "size": 69340,
      "note": "g4",
      "midiNote": 67,
      "velocity": null,
      "dynamic": null,
      "roundRobin": 2
    },
    {
      "file": "g4_p_rr2_dnm.opus",
      "name": "g4_p_rr2_dnm.opus",
      "url": "https://raw.githubusercontent.com/zulfikarbarbora-outl/weresax-opus-48/master/g4_p_rr2_dnm.opus",
      "size": 71981,
      "note": "g4",
      "midiNote": 67,
      "velocity": null,
      "dynamic": null,
      "roundRobin": 2
    },
    {
      "file": "gb2_f_rr1_cnd.opus",
      "name": "gb2_f_rr1_cnd.opus",
      "url": "https://raw.githubusercontent.com/zulfikarbarbora-outl/weresax-opus-48/master/gb2_f_rr1_cnd.opus",
      "size": 46327,
      "note": "gb2",
      "midiNote": 42,
      "velocity": null,
      "dynamic": null,
      "roundRobin": 1
    },
    {
      "file": "gb2_f_rr1_dnm.opus",
      "name": "gb2_f_rr1_dnm.opus",
      "url": "https://raw.githubusercontent.com/zulfikarbarbora-outl/weresax-opus-48/master/gb2_f_rr1_dnm.opus",
      "size": 52017,
      "note": "gb2",
      "midiNote": 42,
      "velocity": null,
      "dynamic": null,
      "roundRobin": 1
    },
    {
      "file": "gb2_f_rr2_cnd.opus",
      "name": "gb2_f_rr2_cnd.opus",
      "url": "https://raw.githubusercontent.com/zulfikarbarbora-outl/weresax-opus-48/master/gb2_f_rr2_cnd.opus",
      "size": 44704,
      "note": "gb2",
      "midiNote": 42,
      "velocity": null,
      "dynamic": null,
      "roundRobin": 2
    },
    {
      "file": "gb2_f_rr2_dnm.opus",
      "name": "gb2_f_rr2_dnm.opus",
      "url": "https://raw.githubusercontent.com/zulfikarbarbora-outl/weresax-opus-48/master/gb2_f_rr2_dnm.opus",
      "size": 49754,
      "note": "gb2",
      "midiNote": 42,
      "velocity": null,
      "dynamic": null,
      "roundRobin": 2
    },
    {
      "file": "gb2_p_rr1_cnd.opus",
      "name": "gb2_p_rr1_cnd.opus",
      "url": "https://raw.githubusercontent.com/zulfikarbarbora-outl/weresax-opus-48/master/gb2_p_rr1_cnd.opus",
      "size": 50039,
      "note": "gb2",
      "midiNote": 42,
      "velocity": null,
      "dynamic": null,
      "roundRobin": 1
    },
    {
      "file": "gb2_p_rr1_dnm.opus",
      "name": "gb2_p_rr1_dnm.opus",
      "url": "https://raw.githubusercontent.com/zulfikarbarbora-outl/weresax-opus-48/master/gb2_p_rr1_dnm.opus",
      "size": 50413,
      "note": "gb2",
      "midiNote": 42,
      "velocity": null,
      "dynamic": null,
      "roundRobin": 1
    },
    {
      "file": "gb2_p_rr2_cnd.opus",
      "name": "gb2_p_rr2_cnd.opus",
      "url": "https://raw.githubusercontent.com/zulfikarbarbora-outl/weresax-opus-48/master/gb2_p_rr2_cnd.opus",
      "size": 48293,
      "note": "gb2",
      "midiNote": 42,
      "velocity": null,
      "dynamic": null,
      "roundRobin": 2
    },
    {
      "file": "gb2_p_rr2_dnm.opus",
      "name": "gb2_p_rr2_dnm.opus",
      "url": "https://raw.githubusercontent.com/zulfikarbarbora-outl/weresax-opus-48/master/gb2_p_rr2_dnm.opus",
      "size": 48730,
      "note": "gb2",
      "midiNote": 42,
      "velocity": null,
      "dynamic": null,
      "roundRobin": 2
    },
    {
      "file": "gb3_f_rr1_cnd.opus",
      "name": "gb3_f_rr1_cnd.opus",
      "url": "https://raw.githubusercontent.com/zulfikarbarbora-outl/weresax-opus-48/master/gb3_f_rr1_cnd.opus",
      "size": 57945,
      "note": "gb3",
      "midiNote": 54,
      "velocity": null,
      "dynamic": null,
      "roundRobin": 1
    },
    {
      "file": "gb3_f_rr1_dnm.opus",
      "name": "gb3_f_rr1_dnm.opus",
      "url": "https://raw.githubusercontent.com/zulfikarbarbora-outl/weresax-opus-48/master/gb3_f_rr1_dnm.opus",
      "size": 60267,
      "note": "gb3",
      "midiNote": 54,
      "velocity": null,
      "dynamic": null,
      "roundRobin": 1
    },
    {
      "file": "gb3_f_rr2_cnd.opus",
      "name": "gb3_f_rr2_cnd.opus",
      "url": "https://raw.githubusercontent.com/zulfikarbarbora-outl/weresax-opus-48/master/gb3_f_rr2_cnd.opus",
      "size": 56745,
      "note": "gb3",
      "midiNote": 54,
      "velocity": null,
      "dynamic": null,
      "roundRobin": 2
    },
    {
      "file": "gb3_f_rr2_dnm.opus",
      "name": "gb3_f_rr2_dnm.opus",
      "url": "https://raw.githubusercontent.com/zulfikarbarbora-outl/weresax-opus-48/master/gb3_f_rr2_dnm.opus",
      "size": 62232,
      "note": "gb3",
      "midiNote": 54,
      "velocity": null,
      "dynamic": null,
      "roundRobin": 2
    },
    {
      "file": "gb3_p_rr1_cnd.opus",
      "name": "gb3_p_rr1_cnd.opus",
      "url": "https://raw.githubusercontent.com/zulfikarbarbora-outl/weresax-opus-48/master/gb3_p_rr1_cnd.opus",
      "size": 43046,
      "note": "gb3",
      "midiNote": 54,
      "velocity": null,
      "dynamic": null,
      "roundRobin": 1
    },
    {
      "file": "gb3_p_rr1_dnm.opus",
      "name": "gb3_p_rr1_dnm.opus",
      "url": "https://raw.githubusercontent.com/zulfikarbarbora-outl/weresax-opus-48/master/gb3_p_rr1_dnm.opus",
      "size": 44677,
      "note": "gb3",
      "midiNote": 54,
      "velocity": null,
      "dynamic": null,
      "roundRobin": 1
    },
    {
      "file": "gb3_p_rr2_cnd.opus",
      "name": "gb3_p_rr2_cnd.opus",
      "url": "https://raw.githubusercontent.com/zulfikarbarbora-outl/weresax-opus-48/master/gb3_p_rr2_cnd.opus",
      "size": 44091,
      "note": "gb3",
      "midiNote": 54,
      "velocity": null,
      "dynamic": null,
      "roundRobin": 2
    },
    {
      "file": "gb3_p_rr2_dnm.opus",
      "name": "gb3_p_rr2_dnm.opus",
      "url": "https://raw.githubusercontent.com/zulfikarbarbora-outl/weresax-opus-48/master/gb3_p_rr2_dnm.opus",
      "size": 52338,
      "note": "gb3",
      "midiNote": 54,
      "velocity": null,
      "dynamic": null,
      "roundRobin": 2
    },
    {
      "file": "gb4_f_rr1_cnd.opus",
      "name": "gb4_f_rr1_cnd.opus",
      "url": "https://raw.githubusercontent.com/zulfikarbarbora-outl/weresax-opus-48/master/gb4_f_rr1_cnd.opus",
      "size": 64055,
      "note": "gb4",
      "midiNote": 66,
      "velocity": null,
      "dynamic": null,
      "roundRobin": 1
    },
    {
      "file": "gb4_f_rr1_dnm.opus",
      "name": "gb4_f_rr1_dnm.opus",
      "url": "https://raw.githubusercontent.com/zulfikarbarbora-outl/weresax-opus-48/master/gb4_f_rr1_dnm.opus",
      "size": 61253,
      "note": "gb4",
      "midiNote": 66,
      "velocity": null,
      "dynamic": null,
      "roundRobin": 1
    },
    {
      "file": "gb4_f_rr2_cnd.opus",
      "name": "gb4_f_rr2_cnd.opus",
      "url": "https://raw.githubusercontent.com/zulfikarbarbora-outl/weresax-opus-48/master/gb4_f_rr2_cnd.opus",
      "size": 53484,
      "note": "gb4",
      "midiNote": 66,
      "velocity": null,
      "dynamic": null,
      "roundRobin": 2
    },
    {
      "file": "gb4_f_rr2_dnm.opus",
      "name": "gb4_f_rr2_dnm.opus",
      "url": "https://raw.githubusercontent.com/zulfikarbarbora-outl/weresax-opus-48/master/gb4_f_rr2_dnm.opus",
      "size": 53923,
      "note": "gb4",
      "midiNote": 66,
      "velocity": null,
      "dynamic": null,
      "roundRobin": 2
    },
    {
      "file": "gb4_p_rr1_cnd.opus",
      "name": "gb4_p_rr1_cnd.opus",
      "url": "https://raw.githubusercontent.com/zulfikarbarbora-outl/weresax-opus-48/master/gb4_p_rr1_cnd.opus",
      "size": 46275,
      "note": "gb4",
      "midiNote": 66,
      "velocity": null,
      "dynamic": null,
      "roundRobin": 1
    },
    {
      "file": "gb4_p_rr1_dnm.opus",
      "name": "gb4_p_rr1_dnm.opus",
      "url": "https://raw.githubusercontent.com/zulfikarbarbora-outl/weresax-opus-48/master/gb4_p_rr1_dnm.opus",
      "size": 49642,
      "note": "gb4",
      "midiNote": 66,
      "velocity": null,
      "dynamic": null,
      "roundRobin": 1
    },
    {
      "file": "gb4_p_rr2_cnd.opus",
      "name": "gb4_p_rr2_cnd.opus",
      "url": "https://raw.githubusercontent.com/zulfikarbarbora-outl/weresax-opus-48/master/gb4_p_rr2_cnd.opus",
      "size": 56611,
      "note": "gb4",
      "midiNote": 66,
      "velocity": null,
      "dynamic": null,
      "roundRobin": 2
    },
    {
      "file": "gb4_p_rr2_dnm.opus",
      "name": "gb4_p_rr2_dnm.opus",
      "url": "https://raw.githubusercontent.com/zulfikarbarbora-outl/weresax-opus-48/master/gb4_p_rr2_dnm.opus",
      "size": 56898,
      "note": "gb4",
      "midiNote": 66,
      "velocity": null,
      "dynamic": null,
      "roundRobin": 2
    }
  ],
  "byNote": {
    "37": [
      "db2_f_rr1_cnd.opus",
      "db2_f_rr1_dnm.opus",
      "db2_f_rr2_cnd.opus",
      "db2_f_rr2_dnm.opus",
      "db2_p_rr1_cnd.opus",
      "db2_p_rr1_dnm.opus",
      "db2_p_rr2_cnd.opus",
      "db2_p_rr2_dnm.opus"
    ],
    "38": [
      "d2_f_rr1_cnd.opus",
      "d2_f_rr1_dnm.opus",
      "d2_f_rr2_cnd.opus",
      "d2_f_rr2_dnm.opus",
      "d2_p_rr1_cnd.opus",
      "d2_p_rr1_dnm.opus",
      "d2_p_rr2_cnd.opus",
      "d2_p_rr2_dnm.opus"
    ],
    "39": [
      "eb2_f_rr1_cnd.opus",
      "eb2_f_rr1_dnm.opus",
      "eb2_f_rr2_cnd.opus",
      "eb2_f_rr2_dnm.opus",
      "eb2_p_rr1_cnd.opus",
      "eb2_p_rr1_dnm.opus",
      "eb2_p_rr2_cnd.opus",
      "eb2_p_rr2_dnm.opus"
    ],
    "40": [
      "e2_f_rr1_cnd.opus",
      "e2_f_rr1_dnm.opus",
      "e2_f_rr2_cnd.opus",
      "e2_f_rr2_dnm.opus",
      "e2_p_rr1_cnd.opus",
      "e2_p_rr1_dnm.opus",
      "e2_p_rr2_cnd.opus",
      "e2_p_rr2_dnm.opus"
    ],
    "41": [
      "f2_f_rr1_cnd.opus",
      "f2_f_rr1_dnm.opus",
      "f2_f_rr2_cnd.opus",
      "f2_f_rr2_dnm.opus",
      "f2_p_rr1_cnd.opus",
      "f2_p_rr1_dnm.opus",
      "f2_p_rr2_cnd.opus",
      "f2_p_rr2_dnm.opus"
    ],
    "42": [
      "gb2_f_rr1_cnd.opus",
      "gb2_f_rr1_dnm.opus",
      "gb2_f_rr2_cnd.opus",
      "gb2_f_rr2_dnm.opus",
      "gb2_p_rr1_cnd.opus",
      "gb2_p_rr1_dnm.opus",
      "gb2_p_rr2_cnd.opus",
      "gb2_p_rr2_dnm.opus"
    ],
    "43": [
      "g2_f_rr1_cnd.opus",
      "g2_f_rr1_dnm.opus",
      "g2_f_rr2_cnd.opus",
      "g2_f_rr2_dnm.opus",
      "g2_p_rr1_cnd.opus",
      "g2_p_rr1_dnm.opus",
      "g2_p_rr2_cnd.opus",
      "g2_p_rr2_dnm.opus"
    ],
    "44": [
      "ab2_f_rr1_cnd.opus",
      "ab2_f_rr1_dnm.opus",
      "ab2_f_rr2_cnd.opus",
      "ab2_f_rr2_dnm.opus",
      "ab2_p_rr1_cnd.opus",
      "ab2_p_rr1_dnm.opus",
      "ab2_p_rr2_cnd.opus",
      "ab2_p_rr2_dnm.opus"
    ],
    "45": [
      "a2_f_rr1_cnd.opus",
      "a2_f_rr1_dnm.opus",
      "a2_f_rr2_cnd.opus",
      "a2_f_rr2_dnm.opus",
      "a2_p_rr1_cnd.opus",
      "a2_p_rr1_dnm.opus",
      "a2_p_rr2_cnd.opus",
      "a2_p_rr2_dnm.opus"
    ],
    "46": [
      "bb2_f_rr1_cnd.opus",
      "bb2_f_rr1_dnm.opus",
      "bb2_f_rr2_cnd.opus",
      "bb2_f_rr2_dnm.opus",
      "bb2_p_rr1_cnd.opus",
      "bb2_p_rr1_dnm.opus",
      "bb2_p_rr2_cnd.opus",
      "bb2_p_rr2_dnm.opus"
    ],
    "47": [
      "b2_f_rr1_cnd.opus",
      "b2_f_rr1_dnm.opus",
      "b2_f_rr2_cnd.opus",
      "b2_f_rr2_dnm.opus",
      "b2_p_rr1_cnd.opus",
      "b2_p_rr1_dnm.opus",
      "b2_p_rr2_cnd.opus",
      "b2_p_rr2_dnm.opus"
    ],
    "48": [
      "c3_f_rr1_cnd.opus",
      "c3_f_rr1_dnm.opus",
      "c3_f_rr2_cnd.opus",
      "c3_f_rr2_dnm.opus",
      "c3_p_rr1_cnd.opus",
      "c3_p_rr1_dnm.opus",
      "c3_p_rr2_cnd.opus",
      "c3_p_rr2_dnm.opus"
    ],
    "49": [
      "db3_f_rr1_cnd.opus",
      "db3_f_rr1_dnm.opus",
      "db3_f_rr2_cnd.opus",
      "db3_f_rr2_dnm.opus",
      "db3_p_rr1_cnd.opus",
      "db3_p_rr1_dnm.opus",
      "db3_p_rr2_cnd.opus",
      "db3_p_rr2_dnm.opus"
    ],
    "50": [
      "d3_f_rr1_cnd.opus",
      "d3_f_rr1_dnm.opus",
      "d3_f_rr2_cnd.opus",
      "d3_f_rr2_dnm.opus",
      "d3_p_rr1_cnd.opus",
      "d3_p_rr1_dnm.opus",
      "d3_p_rr2_cnd.opus",
      "d3_p_rr2_dnm.opus"
    ],
    "51": [
      "eb3_f_rr1_cnd.opus",
      "eb3_f_rr1_dnm.opus",
      "eb3_f_rr2_cnd.opus",
      "eb3_f_rr2_dnm.opus",
      "eb3_p_rr1_cnd.opus",
      "eb3_p_rr1_dnm.opus",
      "eb3_p_rr2_cnd.opus",
      "eb3_p_rr2_dnm.opus"
    ],
    "52": [
      "e3_f_rr1_cnd.opus",
      "e3_f_rr1_dnm.opus",
      "e3_f_rr2_cnd.opus",
      "e3_f_rr2_dnm.opus",
      "e3_p_rr1_cnd.opus",
      "e3_p_rr1_dnm.opus",
      "e3_p_rr2_cnd.opus",
      "e3_p_rr2_dnm.opus"
    ],
    "53": [
      "f3_f_rr1_cnd.opus",
      "f3_f_rr1_dnm.opus",
      "f3_f_rr2_cnd.opus",
      "f3_f_rr2_dnm.opus",
      "f3_p_rr1_cnd.opus",
      "f3_p_rr1_dnm.opus",
      "f3_p_rr2_cnd.opus",
      "f3_p_rr2_dnm.opus"
    ],
    "54": [
      "gb3_f_rr1_cnd.opus",
      "gb3_f_rr1_dnm.opus",
      "gb3_f_rr2_cnd.opus",
      "gb3_f_rr2_dnm.opus",
      "gb3_p_rr1_cnd.opus",
      "gb3_p_rr1_dnm.opus",
      "gb3_p_rr2_cnd.opus",
      "gb3_p_rr2_dnm.opus"
    ],
    "55": [
      "g3_f_rr1_cnd.opus",
      "g3_f_rr1_dnm.opus",
      "g3_f_rr2_cnd.opus",
      "g3_f_rr2_dnm.opus",
      "g3_p_rr1_cnd.opus",
      "g3_p_rr1_dnm.opus",
      "g3_p_rr2_cnd.opus",
      "g3_p_rr2_dnm.opus"
    ],
    "56": [
      "ab3_f_rr1_cnd.opus",
      "ab3_f_rr1_dnm.opus",
      "ab3_f_rr2_cnd.opus",
      "ab3_f_rr2_dnm.opus",
      "ab3_p_rr1_cnd.opus",
      "ab3_p_rr1_dnm.opus",
      "ab3_p_rr2_cnd.opus",
      "ab3_p_rr2_dnm.opus"
    ],
    "57": [
      "a3_f_rr1_cnd.opus",
      "a3_f_rr1_dnm.opus",
      "a3_f_rr2_cnd.opus",
      "a3_f_rr2_dnm.opus",
      "a3_p_rr1_cnd.opus",
      "a3_p_rr1_dnm.opus",
      "a3_p_rr2_cnd.opus",
      "a3_p_rr2_dnm.opus"
    ],
    "58": [
      "bb3_f_rr1_cnd.opus",
      "bb3_f_rr1_dnm.opus",
      "bb3_f_rr2_cnd.opus",
      "bb3_f_rr2_dnm.opus",
      "bb3_p_rr1_cnd.opus",
      "bb3_p_rr1_dnm.opus",
      "bb3_p_rr2_cnd.opus",
      "bb3_p_rr2_dnm.opus"
    ],
    "59": [
      "b3_f_rr1_cnd.opus",
      "b3_f_rr1_dnm.opus",
      "b3_f_rr2_cnd.opus",
      "b3_f_rr2_dnm.opus",
      "b3_p_rr1_cnd.opus",
      "b3_p_rr1_dnm.opus",
      "b3_p_rr2_cnd.opus",
      "b3_p_rr2_dnm.opus"
    ],
    "60": [
      "c4_f_rr1_cnd.opus",
      "c4_f_rr1_dnm.opus",
      "c4_f_rr2_cnd.opus",
      "c4_f_rr2_dnm.opus",
      "c4_p_rr1_cnd.opus",
      "c4_p_rr1_dnm.opus",
      "c4_p_rr2_cnd.opus",
      "c4_p_rr2_dnm.opus"
    ],
    "61": [
      "db4_f_rr1_cnd.opus",
      "db4_f_rr1_dnm.opus",
      "db4_f_rr2_cnd.opus",
      "db4_f_rr2_dnm.opus",
      "db4_p_rr1_cnd.opus",
      "db4_p_rr1_dnm.opus",
      "db4_p_rr2_cnd.opus",
      "db4_p_rr2_dnm.opus"
    ],
    "62": [
      "d4_f_rr1_cnd.opus",
      "d4_f_rr1_dnm.opus",
      "d4_f_rr2_cnd.opus",
      "d4_f_rr2_dnm.opus",
      "d4_p_rr1_cnd.opus",
      "d4_p_rr1_dnm.opus",
      "d4_p_rr2_cnd.opus",
      "d4_p_rr2_dnm.opus"
    ],
    "63": [
      "eb4_f_rr1_cnd.opus",
      "eb4_f_rr1_dnm.opus",
      "eb4_f_rr2_cnd.opus",
      "eb4_f_rr2_dnm.opus",
      "eb4_p_rr1_cnd.opus",
      "eb4_p_rr1_dnm.opus",
      "eb4_p_rr2_cnd.opus",
      "eb4_p_rr2_dnm.opus"
    ],
    "64": [
      "e4_f_rr1_cnd.opus",
      "e4_f_rr1_dnm.opus",
      "e4_f_rr2_cnd.opus",
      "e4_f_rr2_dnm.opus",
      "e4_p_rr1_cnd.opus",
      "e4_p_rr1_dnm.opus",
      "e4_p_rr2_cnd.opus",
      "e4_p_rr2_dnm.opus"
    ],
    "65": [
      "f4_f_rr1_cnd.opus",
      "f4_f_rr1_dnm.opus",
      "f4_f_rr2_cnd.opus",
      "f4_f_rr2_dnm.opus",
      "f4_p_rr1_cnd.opus",
      "f4_p_rr1_dnm.opus",
      "f4_p_rr2_cnd.opus",
      "f4_p_rr2_dnm.opus"
    ],
    "66": [
      "gb4_f_rr1_cnd.opus",
      "gb4_f_rr1_dnm.opus",
      "gb4_f_rr2_cnd.opus",
      "gb4_f_rr2_dnm.opus",
      "gb4_p_rr1_cnd.opus",
      "gb4_p_rr1_dnm.opus",
      "gb4_p_rr2_cnd.opus",
      "gb4_p_rr2_dnm.opus"
    ],
    "67": [
      "g4_f_rr1_cnd.opus",
      "g4_f_rr1_dnm.opus",
      "g4_f_rr2_cnd.opus",
      "g4_f_rr2_dnm.opus",
      "g4_p_rr1_cnd.opus",
      "g4_p_rr1_dnm.opus",
      "g4_p_rr2_cnd.opus",
      "g4_p_rr2_dnm.opus"
    ],
    "68": [
      "ab4_f_rr1_cnd.opus",
      "ab4_f_rr1_dnm.opus",
      "ab4_f_rr2_cnd.opus",
      "ab4_f_rr2_dnm.opus",
      "ab4_p_rr1_cnd.opus",
      "ab4_p_rr1_dnm.opus",
      "ab4_p_rr2_cnd.opus",
      "ab4_p_rr2_dnm.opus"
    ]
  }
}